Workbook

Sheet Raw_Data
A1: PO_Number | B1: PO_Date | C1: Vendor_ID | D1: Vendor_Name | E1: Department | F1: Category | G1: Item_ID | H1: Item_Description | I1: Quantity | J1: Unit_Price_INR | K1: PO_Amount_INR | L1: Payment_Terms | M1: Expected_Delivery_Date | N1: Actual_Delivery_Date | O1: Region | P1: Buyer | Q1: PO_Status | R1: Delivery_Status
A2: PO202500001 | B2: 45772 | C2: V002 | D2: Metro Business Supplies | E2: Finance | F2: Office Supplies | G2: ITM001 | H2: A4 Copier Paper - 500 Sheets | I2: 39 | J2: 232.61 | K2: 9071.79 | L2: Net 30 | M2: 45778 | N2: 45778 | O2: West | P2: Kavya Iyer | Q2: Closed | R2: On Time
A3: PO202600002 | B3: 46175 | C3: V002 | D3: Metro Business Supplies | E3: Sales & Marketing | F3: Office Supplies | G3: ITM003 | H3: Ergonomic Office Chair | I3: 8 | J3: 7237.73 | K3: 57901.84 | L3: Net 45 | M3: 46189 | N3: 46189 | O3: West | P3: Ishita Shah | Q3: Closed | R3: On Time
A4: PO202500003 | B4: 46006 | C4: V003 | D4: Prime Workplace India | E4: Operations | F4: Facilities | G4: ITM010 | H4: Printer Maintenance Kit | I4: 14 | J4: 5597.17 | K4: 78360.38 | L4: Net 45 | M4: 46016 | N4: 46016 | O4: South | P4: Rohit Mehta | Q4: Closed | R4: On Time
A5: PO202500004 | B5: 45738 | C5: V015 | D5: TalentBridge Consulting | E5: IT | F5: Professional Services | G5: ITM020 | H5: Audit Support - Monthly | I5: 1 | J5: 53142.53 | K5: 53142.53 | L5: Net 60 | M5: 45755 | N5: 45755 | O5: South | P5: Vikram Reddy | Q5: Closed | R5: On Time
A6: PO202500005 | B6: 45942 | C6: V005 | D6: Vertex Digital Systems | E6: IT | F6: Technology | G6: ITM006 | H6: Business Laptop - Standard | I6: 2 | J6: 64463.55 | K6: 128927.1 | L6: Net 30 | M6: 45956 | N6: 45955 | O6: East | P6: Vikram Reddy | Q6: Closed | R6: On Time
A7: PO202500006 | B7: 45715 | C7: V003 | D7: Prime Workplace India | E7: Operations | F7: Facilities | G7: ITM013 | H7: Electrical Maintenance Service | I7: 6 | J7: 19379.08 | K7: 116274.48 | L7: Net 60 | M7: 45723 | N7: 45720 | O7: East | P7: Ananya Rao | Q7: Closed | R7: On Time
A8: PO202500007 | B8: 45929 | C8: V016 | D8: StratEdge Partners | E8: IT | F8: Professional Services | G8: ITM022 | H8: Data Reporting Support - Monthly | I8: 1 | J8: 46371.25 | K8: 46371.25 | L8: Net 45 | M8: 45936 | N8: 45936 | O8: South | P8: Vikram Reddy | Q8: Closed | R8: On Time
A9: PO202600008 | B9: 46090 | C9: V006 | D9: CoreTech Solutions | E9: Human Resources | F9: Technology | G9: ITM007 | H9: USB-C Docking Station | I9: 14 | J9: 8482.87 | K9: 118760.18 | L9: Net 45 | M9: 46095 | N9: 46095 | O9: North | P9: Neha Kapoor | Q9: Closed | R9: On Time
A10: PO202500009 | B10: 45772 | C10: V003 | D10: Prime Workplace India | E10: Operations | F10: Office Supplies | G10: ITM003 | H10: Ergonomic Office Chair | I10: 9 | J10: 8210 | K10: 73890 | L10: Net 60 | M10: 45789 | N10: 45789 | O10: North | P10: Ananya Rao | Q10: Closed | R10: On Time
A11: PO202500010 | B11: 45814 | C11: V011 | D11: ProSafe Equipment | E11: Operations | F11: Safety | G11: ITM014 | H11: Safety Gloves - Box | I11: 12 | J11: 686.72 | K11: 8240.64 | L11: Net 30 | M11: 45824 | N11: 45822 | O11: West | P11: Ananya Rao | Q11: Closed | R11: On Time
A12: PO202500011 | B12: 45745 | C12: V006 | D12: CoreTech Solutions | E12: IT | F12: Technology | G12: ITM005 | H12: 24-inch Business Monitor | I12: 3 | J12: 10652.85 | K12: 31958.55 | L12: Net 60 | M12: 45754 | N12: 45751 | O12: West | P12: Vikram Reddy | Q12: Closed | R12: On Time
A13: PO202600012 | B13: 46040 | C13: V012 | D13: BrightReach Media | E13: Sales & Marketing | F13: Marketing | G13: ITM017 | H13: Digital Marketing Campaign | I13: 3 | J13: 41597.96 | K13: 124793.88 | L13: Net 30 | M13: 46053 | N13: 46052 | O13: South | P13: Arjun Nair | Q13: Closed | R13: On Time
... A45: PO202600044 | B45: 46158 | C45: V014 | D45: Insight Advisory Services | E45: Finance | F45: Professional Services | G45: ITM022 | H45: Data Reporting Support - Monthly | I45: 1 | J45: 46154.49 | K45: 46154.49 | L45: Net 30 | M45: 46166 | N45: 46165 | O45: North | P45: Kavya Iyer | Q45: Closed | R45: On Time
A46: PO202600045 | B46: 46201 | C46: V014 | D46: Insight Advisory Services | E46: Administration | F46: Professional Services | G46: ITM021 | H46: Recruitment Service Fee | I46: 1 | J46: 45037.67 | K46: 45037.67 | L46: Net 45 | M46: 46210 | O46: West | P46: Meera Joshi | Q46: Open | R46: Open
A47: PO202500046 | B47: 45941 | C47: V016 | D47: StratEdge Partners | E47: Administration | F47: Professional Services | G47: ITM021 | H47: Recruitment Service Fee | I47: 1 | J47: 45174.98 | K47: 45174.98 | L47: Net 30 | M47: 45949 | N47: 45947 | O47: West | P47: Meera Joshi | Q47: Closed | R47: On Time
A48: PO202500047 | B48: 45957 | C48: V009 | D48: Urban Maintenance Co. | E48: Operations | F48: Facilities | G48: ITM010 | H48: Printer Maintenance Kit | I48: 8 | J48: 5244.48 | K48: 41955.84 | L48: Net 60 | M48: 45969 | N48: 45968 | O48: North | P48: Rohit Mehta | Q48: Closed | R48: On Time
A49: PO202600048 | B49: 46068 | C49: V001 | D49: Apex Office Solutions | E49: Sales & Marketing | F49: Office Supplies | G49: ITM001 | H49: A4 Copier Paper - 500 Sheets | I49: 24 | J49: 253.09 | K49: 6074.16 | L49: Net 45 | M49: 46074 | N49: 46074 | O49: East | P49: Arjun Nair | Q49: Closed | R49: On Time
A50: PO202600049 | B50: 46193 | C50: V003 | D50: Prime Workplace India | E50: Administration | F50: Facilities | G50: ITM013 | H50: Electrical Maintenance Service | I50: 2 | J50: 20109.59 | K50: 40219.18 | L50: Net 30 | M50: 46210 | O50: West | P50: Meera Joshi | Q50: Open | R50: Open
A51: PO202500050 | B51: 45734 | C51: V006 | D51: CoreTech Solutions | E51: Human Resources | F51: Technology | G51: ITM008 | H51: Network Switch - 24 Port | I51: 5 | J51: 14721.39 | K51: 73606.95 | L51: Net 30 | M51: 45750 | N51: 45747 | O51: West | P51: Neha Kapoor | Q51: Closed | R51: On Time
A52: PO202500051 | B52: 45860 | C52: V003 | D52: Prime Workplace India | E52: Sales & Marketing | F52: Office Supplies | G52: ITM001 | H52: A4 Copier Paper - 500 Sheets | I52: 9 | J52: 271.17 | K52: 2440.53 | L52: Net 45 | M52: 45865 | N52: 45863 | O52: North | P52: Ishita Shah | Q52: Closed | R52: On Time
A53: PO202500052 | B53: 45785 | C53: V015 | D53: TalentBridge Consulting | E53: Finance | F53: Professional Services | G53: ITM021 | H53: Recruitment Service Fee | I53: 1 | J53: 47911.86 | K53: 47911.86 | L53: Net 45 | M53: 45799 | N53: 45807 | O53: North | P53: Kavya Iyer | Q53: Closed | R53: Late
A54: PO202500053 | B54: 45751 | C54: V006 | D54: CoreTech Solutions | E54: IT | F54: Technology | G54: ITM009 | H54: Annual Software License | I54: 3 | J54: 20717.88 | K54: 62153.64 | L54: Net 60 | M54: 45763 | N54: 45760 | O54: West | P54: Vikram Reddy | Q54: Closed | R54: On Time
A55: PO202600054 | B55: 46139 | C55: V007 | D55: SecureNet Systems | E55: Finance | F55: Technology | G55: ITM004 | H55: Wireless Keyboard & Mouse | I55: 49 | J55: 1867.53 | K55: 91508.97 | L55: Net 45 | M55: 46151 | N55: 46148 | O55: South | P55: Kavya Iyer | Q55: Closed | R55: On Time
A56: PO202500055 | B56: 45748 | C56: V015 | D56: TalentBridge Consulting | E56: Finance | F56: Professional Services | G56: ITM019 | H56: Training Workshop - Per Batch | I56: 2 | J56: 40635.81 | K56: 81271.62 | L56: Net 45 | M56: 45753 | N56: 45751 | O56: East | P56: Kavya Iyer | Q56: Closed | R56: On Time
A57: PO202500056 | B57: 45710 | C57: V007 | D57: SecureNet Systems | E57: Sales & Marketing | F57: Technology | G57: ITM007 | H57: USB-C Docking Station | I57: 1 | J57: 9110.9 | K57: 9110.9 | L57: Net 45 | M57: 45725 | N57: 45724 | O57: North | P57: Arjun Nair | Q57: Closed | R57: On Time
A58: PO202600057 | B58: 46075 | C58: V003 | D58: Prime Workplace India | E58: Administration | F58: Office Supplies | G58: ITM002 | H58: Black Toner Cartridge | I58: 3 | J58: 3638.09 | K58: 10914.27 | L58: Net 30 | M58: 46087 | N58: 46085 | O58: North | P58: Meera Joshi | Q58: Closed | R58: On Time
A59: PO202500058 | B59: 45907 | C59: V002 | D59: Metro Business Supplies | E59: Operations | F59: Office Supplies | G59: ITM003 | H59: Ergonomic Office Chair | I59: 14 | J59: 7537.92 | K59: 105530.88 | L59: Net 30 | M59: 45913 | N59: 45910 | O59: North | P59: Ananya Rao | Q59: Closed | R59: On Time
A60: PO202500059 | B60: 45947 | C60: V014 | D60: Insight Advisory Services | E60: IT | F60: Professional Services | G60: ITM020 | H60: Audit Support - Monthly | I60: 1 | J60: 52186.72 | K60: 52186.72 | L60: Net 30 | M60: 45960 | N60: 45957 | O60: North | P60: Vikram Reddy | Q60: Closed | R60: On Time
A61: PO202500060 | B61: 45902 | C61: V003 | D61: Prime Workplace India | E61: Operations | F61: Facilities | G61: ITM010 | H61: Printer Maintenance Kit | I61: 15 | J61: 5792.84 | K61: 86892.6 | L61: Net 30 | M61: 45919 | N61: 45918 | O61: South | P61: Ananya Rao | Q61: Closed | R61: On Time
A62: PO202600061 | B62: 46108 | C62: V001 | D62: Apex Office Solutions | E62: Administration | F62: Office Supplies | G62: ITM003 | H62: Ergonomic Office Chair | I62: 3 | J62: 8585.36 | K62: 25756.08 | L62: Net 30 | M62: 46114 | N62: 46112 | O62: East | P62: Meera Joshi | Q62: Closed | R62: On Time
... A96: PO202500095 | B96: 45948 | C96: V014 | D96: Insight Advisory Services | E96: Administration | F96: Professional Services | G96: ITM020 | H96: Audit Support - Monthly | I96: 1 | J96: 52647.22 | K96: 52647.22 | L96: Net 30 | M96: 45958 | N96: 45955 | O96: South | P96: Meera Joshi | Q96: Closed | R96: On Time
A97: PO202600096 | B97: 46197 | C97: V014 | D97: Insight Advisory Services | E97: IT | F97: Professional Services | G97: ITM019 | H97: Training Workshop - Per Batch | I97: 1 | J97: 37096.5 | K97: 37096.5 | L97: Net 60 | M97: 46207 | O97: West | P97: Vikram Reddy | Q97: Open | R97: Open
A98: PO202500097 | B98: 45761 | C98: V001 | D98: Apex Office Solutions | E98: Sales & Marketing | F98: Office Supplies | G98: ITM003 | H98: Ergonomic Office Chair | I98: 13 | J98: 7724.41 | K98: 100417.33 | L98: Net 30 | M98: 45775 | N98: 45772 | O98: West | P98: Arjun Nair | Q98: Closed | R98: On Time
A99: PO202600098 | B99: 46106 | C99: V007 | D99: SecureNet Systems | E99: Human Resources | F99: Technology | G99: ITM005 | H99: 24-inch Business Monitor | I99: 8 | J99: 11594.83 | K99: 92758.64 | L99: Net 60 | M99: 46114 | N99: 46112 | O99: East | P99: Neha Kapoor | Q99: Closed | R99: On Time
A100: PO202600099 | B100: 46109 | C100: V016 | D100: StratEdge Partners | E100: Finance | F100: Professional Services | G100: ITM022 | H100: Data Reporting Support - Monthly | I100: 3 | J100: 48120.7 | K100: 144362.1 | L100: Net 45 | M100: 46116 | N100: 46116 | O100: North | P100: Kavya Iyer | Q100: Closed | R100: On Time
A101: PO202500100 | B101: 45949 | C101: V009 | D101: Urban Maintenance Co. | E101: Operations | F101: Facilities | G101: ITM011 | H101: Cleaning Supplies Kit | I101: 19 | J101: 1254.86 | K101: 23842.34 | L101: Net 60 | M101: 45967 | N101: 45965 | O101: East | P101: Ananya Rao | Q101: Closed | R101: On Time
A102: PO202600101 | B102: 46063 | C102: V001 | D102: Apex Office Solutions | E102: Operations | F102: Office Supplies | G102: ITM002 | H102: Black Toner Cartridge | I102: 2 | J102: 3114.35 | K102: 6228.7 | L102: Net 45 | M102: 46081 | N102: 46079 | O102: West | P102: Ananya Rao | Q102: Closed | R102: On Time
A103: PO202600102 | B103: 46138 | C103: V001 | D103: Apex Office Solutions | E103: Operations | F103: Office Supplies | G103: ITM001 | H103: A4 Copier Paper - 500 Sheets | I103: 40 | J103: 253.61 | K103: 10144.4 | L103: Net 30 | M103: 46154 | N103: 46151 | O103: North | P103: Ananya Rao | Q103: Closed | R103: On Time
A104: PO202500103 | B104: 45966 | C104: V010 | D104: SafeGuard Industrial | E104: Operations | F104: Safety | G104: ITM016 | H104: First Aid Refill Kit | I104: 36 | J104: 2057.32 | K104: 74063.52 | L104: Net 45 | M104: 45980 | N104: 45979 | O104: North | P104: Rohit Mehta | Q104: Closed | R104: On Time
A105: PO202500104 | B105: 45659 | C105: V015 | D105: TalentBridge Consulting | E105: Finance | F105: Professional Services | G105: ITM020 | H105: Audit Support - Monthly | I105: 1 | J105: 53339.91 | K105: 53339.91 | L105: Net 30 | M105: 45665 | N105: 45665 | O105: East | P105: Kavya Iyer | Q105: Closed | R105: On Time
A106: PO202500105 | B106: 46011 | C106: V006 | D106: CoreTech Solutions | E106: IT | F106: Technology | G106: ITM008 | H106: Network Switch - 24 Port | I106: 1 | J106: 15134 | K106: 15134 | L106: Net 45 | M106: 46021 | N106: 46020 | O106: East | P106: Vikram Reddy | Q106: Closed | R106: On Time
A107: PO202500106 | B107: 45722 | C107: V001 | D107: Apex Office Solutions | E107: Administration | F107: Office Supplies | G107: ITM002 | H107: Black Toner Cartridge | I107: 15 | J107: 3443.18 | K107: 51647.7 | L107: Net 30 | M107: 45727 | N107: 45725 | O107: East | P107: Meera Joshi | Q107: Closed | R107: On Time
A108: PO202500107 | B108: 45853 | C108: V001 | D108: Apex Office Solutions | E108: Administration | F108: Office Supplies | G108: ITM003 | H108: Ergonomic Office Chair | I108: 6 | J108: 8029.9 | K108: 48179.4 | L108: Net 60 | M108: 45864 | N108: 45861 | O108: East | P108: Meera Joshi | Q108: Closed | R108: On Time
A109: PO202500108 | B109: 45849 | C109: V003 | D109: Prime Workplace India | E109: Sales & Marketing | F109: Office Supplies | G109: ITM002 | H109: Black Toner Cartridge | I109: 2 | J109: 3456.24 | K109: 6912.48 | L109: Net 30 | M109: 45860 | N109: 45859 | O109: North | P109: Arjun Nair | Q109: Closed | R109: On Time
... A263: PO202500262 | B263: 45997 | C263: V006 | D263: CoreTech Solutions | E263: Sales & Marketing | F263: Technology | G263: ITM009 | H263: Annual Software License | I263: 2 | J263: 20975.25 | K263: 41950.5 | L263: Net 30 | M263: 46003 | N263: 46002 | O263: North | P263: Ishita Shah | Q263: Closed | R263: On Time
A264: PO202600263 | B264: 46192 | C264: V001 | D264: Apex Office Solutions | E264: Operations | F264: Office Supplies | G264: ITM002 | H264: Black Toner Cartridge | I264: 12 | J264: 3227.23 | K264: 38726.76 | L264: Net 60 | M264: 46203 | O264: East | P264: Ananya Rao | Q264: Open | R264: Open
A265: PO202600264 | B265: 46119 | C265: V003 | D265: Prime Workplace India | E265: Sales & Marketing | F265: Office Supplies | G265: ITM001 | H265: A4 Copier Paper - 500 Sheets | I265: 52 | J265: 251.77 | K265: 13092.04 | L265: Net 45 | M265: 46124 | N265: 46121 | O265: East | P265: Arjun Nair | Q265: Closed | R265: On Time
A266: PO202500265 | B266: 45789 | C266: V014 | D266: Insight Advisory Services | E266: IT | F266: Professional Services | G266: ITM022 | H266: Data Reporting Support - Monthly | I266: 1 | J266: 48710.85 | K266: 48710.85 | L266: Net 60 | M266: 45798 | N266: 45796 | O266: East | P266: Vikram Reddy | Q266: Closed | R266: On Time
A267: PO202500266 | B267: 45799 | C267: V015 | D267: TalentBridge Consulting | E267: IT | F267: Professional Services | G267: ITM021 | H267: Recruitment Service Fee | I267: 1 | J267: 49808.15 | K267: 49808.15 | L267: Net 45 | M267: 45807 | N267: 45805 | O267: West | P267: Vikram Reddy | Q267: Closed | R267: On Time
A268: PO202600267 | B268: 46173 | C268: V002 | D268: Metro Business Supplies | E268: Sales & Marketing | F268: Office Supplies | G268: ITM001 | H268: A4 Copier Paper - 500 Sheets | I268: 42 | J268: 230.27 | K268: 9671.34 | L268: Net 45 | M268: 46187 | N268: 46184 | O268: North | P268: Ishita Shah | Q268: Closed | R268: On Time
A269: PO202500268 | B269: 45671 | C269: V002 | D269: Metro Business Supplies | E269: Operations | F269: Office Supplies | G269: ITM001 | H269: A4 Copier Paper - 500 Sheets | I269: 53 | J269: 222.84 | K269: 11810.52 | L269: Net 45 | M269: 45688 | N269: 45694 | O269: West | P269: Ananya Rao | Q269: Closed | R269: Late
A270: PO202500269 | B270: 45960 | C270: V004 | D270: Nexa Technologies | E270: Sales & Marketing | F270: Technology | G270: ITM007 | H270: USB-C Docking Station | I270: 12 | J270: 9054.51 | K270: 108654.12 | L270: Net 30 | M270: 45973 | N270: 45970 | O270: North | P270: Arjun Nair | Q270: Closed | R270: On Time
A271: PO202600270 | B271: 46048 | C271: V016 | D271: StratEdge Partners | E271: Administration | F271: Professional Services | G271: ITM021 | H271: Recruitment Service Fee | I271: 1 | J271: 42115.36 | K271: 42115.36 | L271: Net 45 | M271: 46056 | N271: 46053 | O271: North | P271: Meera Joshi | Q271: Closed | R271: On Time
A272: PO202500271 | B272: 45856 | C272: V010 | D272: SafeGuard Industrial | E272: Operations | F272: Safety | G272: ITM014 | H272: Safety Gloves - Box | I272: 37 | J272: 709.49 | K272: 26251.13 | L272: Net 30 | M272: 45862 | N272: 45859 | O272: North | P272: Ananya Rao | Q272: Closed | R272: On Time
A273: PO202500272 | B273: 45822 | C273: V015 | D273: TalentBridge Consulting | E273: Finance | F273: Professional Services | G273: ITM022 | H273: Data Reporting Support - Monthly | I273: 1 | J273: 49553.69 | K273: 49553.69 | L273: Net 30 | M273: 45832 | N273: 45830 | O273: North | P273: Kavya Iyer | Q273: Closed | R273: On Time
A274: PO202500273 | B274: 45983 | C274: V016 | D274: StratEdge Partners | E274: Administration | F274: Professional Services | G274: ITM019 | H274: Training Workshop - Per Batch | I274: 3 | J274: 35914.3 | K274: 107742.9 | L274: Net 30 | M274: 45996 | N274: 45994 | O274: West | P274: Meera Joshi | Q274: Closed | R274: On Time
A275: PO202500274 | B275: 45997 | C275: V010 | D275: SafeGuard Industrial | E275: Operations | F275: Safety | G275: ITM016 | H275: First Aid Refill Kit | I275: 53 | J275: 2143.31 | K275: 113595.43 | L275: Net 30 | M275: 46012 | N275: 46024 | O275: West | P275: Ananya Rao | Q275: Closed | R275: Late
A276: PO202500275 | B276: 45986 | C276: V005 | D276: Vertex Digital Systems | E276: IT | F276: Technology | G276: ITM007 | H276: USB-C Docking Station | I276: 1 | J276: 9853.82 | K276: 9853.82 | L276: Net 30 | M276: 45999 | N276: 45997 | O276: East | P276: Vikram Reddy | Q276: Closed | R276: On Time
... A298: PO202600297 | B298: 46048 | C298: V004 | D298: Nexa Technologies | E298: IT | F298: Technology | G298: ITM007 | H298: USB-C Docking Station | I298: 4 | J298: 8747.67 | K298: 34990.68 | L298: Net 30 | M298: 46066 | N298: 46063 | O298: South | P298: VIKRAM REDDY | Q298: Closed | R298: On Time
A299: PO202600298 | B299: 46193 | C299: V011 | D299: ProSafe Equipment | E299: Operations | F299: Safety | G299: ITM014 | H299: Safety Gloves - Box | I299: 28 | J299: 676.09 | K299: 18930.52 | L299: Net 30 | M299: 46199 | O299: North | P299: Rohit Mehta | Q299: Open | R299: Open
A300: PO202600299 | B300: 46081 | C300: V013 | D300: MarketCraft Communications | E300: Sales & Marketing | F300: Marketing | G300: ITM018 | H300: Printed Marketing Materials | I300: 1 | J300: 13798.65 | K300: 13798.65 | L300: Net 45 | M300: 46095 | N300: 46092 | O300: South | P300: Arjun Nair | Q300: Closed | R300: On Time
A301: PO202500300 | B301: 45823 | C301: V006 | D301: CoreTech Solutions | E301: Sales & Marketing | F301: Technology | G301: ITM008 | H301: Network Switch - 24 Port | I301: 1 | J301: 15618.39 | K301: 15618.39 | L301: Net 45 | M301: 45830 | N301: 45830 | O301: West | P301: Ishita Shah | Q301: Closed | R301: On Time
A302: PO202600301 | B302: 46103 | C302: V015 | D302: TalentBridge Consulting | E302: Finance | F302: Professional Services | G302: ITM019 | H302: Training Workshop - Per Batch | I302: 2 | J302: 41295.24 | K302: 82590.48 | L302: Net 45 | M302: 46117 | N302: 46115 | O302: South | P302: Kavya Iyer | Q302: Closed | R302: On Time
A303: PO202600302 | B303: 46164 | C303: V010 | D303: SafeGuard Industrial | E303: Operations | F303: Safety | G303: ITM016 | H303: First Aid Refill Kit | I303: 43 | J303: 2042.58 | K303: 87830.94 | L303: Net 45 | M303: 46177 | N303: 46176 | O303: South | P303: Rohit Mehta | Q303: Closed | R303: On Time
A304: PO202500303 | B304: 45819 | C304: V015 | D304: TalentBridge Consulting | E304: Finance | F304: Professional Services | G304: ITM021 | H304: Recruitment Service Fee | I304: 1 | J304: 47532.6 | K304: 47532.6 | L304: Net 30 | M304: 45832 | N304: 45845 | O304: South | P304: Kavya Iyer | Q304: Closed | R304: Late
A305: PO202500304 | B305: 46014 | C305: V007 | D305: SecureNet Systems | E305: IT | F305: Technology | G305: ITM008 | H305: Network Switch - 24 Port | I305: 7 | J305: 17151.91 | K305: 120063.37 | L305: Net 30 | M305: 46028 | N305: 46032 | O305: South | P305: Vikram Reddy | Q305: Closed | R305: Late
A306: PO202600305 | B306: 46173 | C306: V016 | D306: StratEdge Partners | E306: Administration | F306: Professional Services | G306: ITM021 | H306: Recruitment Service Fee | I306: 3 | J306: 45098.45 | K306: 135295.35 | L306: Net 45 | M306: 46182 | N306: 46179 | O306: West | P306: Meera Joshi | Q306: Closed | R306: On Time
A307: PO202500306 | B307: 45686 | C307: V015 | D307: TalentBridge Consulting | E307: Finance | F307: Professional Services | G307: ITM020 | H307: Audit Support - Monthly | I307: 1 | J307: 54055.84 | K307: 54055.84 | L307: Net 45 | M307: 45697 | N307: 45697 | O307: North | P307: Kavya Iyer | Q307: Closed | R307: On Time
A308: PO202500307 | B308: 45952 | C308: V015 | D308: TalentBridge Consulting | E308: IT | F308: Professional Services | G308: ITM019 | H308: Training Workshop - Per Batch | I308: 1 | J308: 39315.85 | K308: 39315.85 | L308: Net 30 | M308: 45962 | N308: 45960 | O308: West | P308: Vikram Reddy | Q308: Closed | R308: On Time
A309: PO202500308 | B309: 45862 | C309: V014 | D309: Insight Advisory Services | E309: Finance | F309: Professional Services | G309: ITM020 | H309: Audit Support - Monthly | I309: 3 | J309: 53827.52 | K309: 161482.56 | L309: Net 30 | M309: 45872 | N309: 45872 | O309: South | P309: Kavya Iyer | Q309: Closed | R309: On Time
A310: PO202600309 | B310: 46038 | C310: V002 | D310: Metro Business Supplies | E310: Sales & Marketing | F310: Office Supplies | G310: ITM002 | H310: Black Toner Cartridge | I310: 15 | J310: 3071.86 | K310: 46077.9 | L310: Net 45 | M310: 46051 | N310: 46050 | O310: West | P310: Arjun Nair | Q310: Closed | R310: On Time
A311: PO202500310 | B311: 45691 | C311: V006 | D311: CoreTech Solutions | E311: Human Resources | F311: Technology | G311: ITM005 | H311: 24-inch Business Monitor | I311: 8 | J311: 9894.73 | K311: 79157.84 | L311: Net 45 | M311: 45701 | N311: 45701 | O311: East | P311: Neha Kapoor | Q311: Closed | R311: On Time
... A350: PO202600349 | B350: 46118 | C350: V004 | D350: Nexa Technologies | E350: Finance | F350: Technology | G350: ITM008 | H350: Network Switch - 24 Port | I350: 5 | J350: 16615.11 | K350: 83075.55 | L350: Net 45 | M350: 46131 | N350: 46130 | O350: South | P350: Kavya Iyer | Q350: Closed | R350: On Time
A351: PO202600350 | B351: 46197 | C351: V009 | D351: Urban Maintenance Co. | E351: Operations | F351: Facilities | G351: ITM011 | H351: Cleaning Supplies Kit | I351: 8 | J351: 1316.24 | K351: 10529.92 | L351: Net 45 | M351: 46209 | O351: North | P351: Ananya Rao | Q351: Open | R351: Open
A352: PO202500351 | B352: 45677 | C352: V009 | D352: Urban Maintenance Co. | E352: Administration | F352: Facilities | G352: ITM011 | H352: Cleaning Supplies Kit | I352: 50 | J352: 1303.48 | K352: 65174 | L352: Net 60 | M352: 45683 | N352: 45680 | O352: South | P352: Meera Joshi | Q352: Closed | R352: On Time
A353: PO202500352 | B353: 45861 | C353: V004 | D353: Nexa Technologies | E353: Human Resources | F353: Technology | G353: ITM004 | H353: Wireless Keyboard & Mouse | I353: 24 | J353: 1890.97 | K353: 45383.28 | L353: Net 30 | M353: 45871 | N353: 45870 | O353: North | P353: Neha Kapoor | Q353: Closed | R353: On Time
A354: PO202500353 | B354: 45967 | C354: V016 | D354: StratEdge Partners | E354: Administration | F354: Professional Services | G354: ITM021 | H354: Recruitment Service Fee | I354: 2 | J354: 44362.43 | K354: 88724.86 | L354: Net 30 | M354: 45985 | N354: 45983 | O354: North | P354: Meera Joshi | Q354: Closed | R354: On Time
A355: PO202500354 | B355: 45798 | C355: V007 | D355: SecureNet Systems | E355: Human Resources | F355: Technology | G355: ITM008 | H355: Network Switch - 24 Port | I355: 7 | J355: 17509.34 | K355: 122565.38 | L355: Net 60 | M355: 45806 | N355: 45803 | O355: North | P355: Neha Kapoor | Q355: Closed | R355: On Time
A356: PO202500355 | B356: 45792 | C356: V011 | D356: ProSafe Equipment | E356: Operations | F356: Safety | G356: ITM016 | H356: First Aid Refill Kit | I356: 24 | J356: 2070.08 | K356: 49681.92 | L356: Net 30 | M356: 45808 | N356: 45807 | O356: West | P356: Ananya Rao | Q356: Closed | R356: On Time
A357: PO202500356 | B357: 45983 | C357: V001 | D357: Apex Office Solutions | E357: Sales & Marketing | F357: Office Supplies | G357: ITM001 | H357: A4 Copier Paper - 500 Sheets | I357: 14 | J357: 253.71 | K357: 3551.94 | L357: Net 60 | M357: 45999 | N357: 46006 | O357: East | P357: Ishita Shah | Q357: Closed | R357: Late
A358: PO202500357 | B358: 45968 | C358: V014 | D358: Insight Advisory Services | E358: Administration | F358: Professional Services | G358: ITM021 | H358: Recruitment Service Fee | I358: 1 | J358: 43961.13 | K358: 43961.13 | L358: Net 45 | M358: 45975 | N358: 45986 | O358: West | P358: Meera Joshi | Q358: Closed | R358: Late
A359: PO202600358 | B359: 46025 | C359: V006 | D359: CoreTech Solutions | E359: IT | F359: Technology | G359: ITM008 | H359: Network Switch - 24 Port | I359: 6 | J359: 15321.46 | K359: 91928.76 | L359: Net 30 | M359: 46032 | N359: 46029 | O359: West | P359: Vikram Reddy | Q359: Closed | R359: On Time
A360: PO202500359 | B360: 45889 | C360: V007 | D360: SecureNet Systems | E360: IT | F360: Technology | G360: ITM006 | H360: Business Laptop - Standard | I360: 4 | J360: 58478.38 | K360: 233913.52 | L360: Net 60 | M360: 45906 | N360: 45905 | O360: East | P360: Vikram Reddy | Q360: Closed | R360: On Time
A361: PO202500360 | B361: 45910 | C361: V014 | D361: Insight Advisory Services | E361: IT | F361: Professional Services | G361: ITM021 | H361: Recruitment Service Fee | I361: 3 | J361: 47003.51 | K361: 141010.53 | L361: Net 30 | M361: 45924 | N361: 45924 | O361: East | P361: Vikram Reddy | Q361: Closed | R361: On Time
A362: PO202500361 | B362: 45909 | C362: V006 | D362: CoreTech Solutions | E362: Human Resources | F362: Technology | G362: ITM004 | H362: Wireless Keyboard & Mouse | I362: 45 | J362: 1694.36 | K362: 76246.2 | L362: Net 30 | M362: 45914 | N362: 45923 | O362: North | P362: Neha Kapoor | Q362: Closed | R362: Late
A363: PO202600362 | B363: 46130 | C363: V002 | D363: Metro Business Supplies | E363: Finance | F363: Office Supplies | G363: ITM003 | H363: Ergonomic Office Chair | I363: 14 | J363: 7056.7 | K363: 98793.8 | L363: Net 30 | M363: 46145 | N363: 46145 | O363: West | P363: Kavya Iyer | Q363: Closed | R363: On Time
... A626: PO202500625 | B626: 46022 | C626: V014 | D626: Insight Advisory Services | E626: Human Resources | F626: Professional Services | G626: ITM021 | H626: Recruitment Service Fee | I626: 1 | J626: 44616.37 | K626: 44616.37 | L626: Net 30 | M626: 46033 | N626: 46033 | O626: West | P626: Neha Kapoor | Q626: Closed | R626: On Time
A627: PO202600626 | B627: 46199 | C627: V001 | D627: Apex Office Solutions | E627: Operations | F627: Office Supplies | G627: ITM002 | H627: Black Toner Cartridge | I627: 5 | J627: 3242.14 | K627: 16210.7 | L627: Net 30 | M627: 46207 | O627: West | P627: Rohit Mehta | Q627: Open | R627: Open
A628: PO202600627 | B628: 46107 | C628: V014 | D628: Insight Advisory Services | E628: Finance | F628: Professional Services | G628: ITM019 | H628: Training Workshop - Per Batch | I628: 1 | J628: 39457.16 | K628: 39457.16 | L628: Net 30 | M628: 46113 | N628: 46113 | O628: East | P628: Kavya Iyer | Q628: Closed | R628: On Time
A629: PO202500628 | B629: 45690 | C629: V003 | D629: Prime Workplace India | E629: Operations | F629: Facilities | G629: ITM012 | H629: LED Panel Light | I629: 36 | J629: 1772.59 | K629: 63813.24 | L629: Net 30 | M629: 45707 | N629: 45706 | O629: East | P629: Rohit Mehta | Q629: Closed | R629: On Time
A630: PO202500629 | B630: 45792 | C630: V001 | D630: Apex Office Solutions | E630: Operations | F630: Office Supplies | G630: ITM001 | H630: A4 Copier Paper - 500 Sheets | I630: 54 | J630: 246.23 | K630: 13296.42 | L630: Net 30 | M630: 45807 | N630: 45805 | O630: South | P630: Rohit Mehta | Q630: Closed | R630: On Time
A631: PO202600630 | B631: 46149 | C631: V006 | D631: CoreTech Solutions | E631: Sales & Marketing | F631: Technology | G631: ITM005 | H631: 24-inch Business Monitor | I631: 3 | J631: 10453.25 | K631: 31359.75 | L631: Net 60 | M631: 46157 | N631: 46157 | O631: West | P631: Ishita Shah | Q631: Closed | R631: On Time
A632: PO202500631 | B632: 45861 | C632: V006 | D632: CoreTech Solutions | E632: IT | F632: Technology | G632: ITM009 | H632: Annual Software License | I632: 4 | J632: 20782.11 | K632: 83128.44 | L632: Net 30 | M632: 45879 | N632: 45878 | O632: West | P632: Vikram Reddy | Q632: Closed | R632: On Time
A633: PO202500632 | B633: 45697 | C633: V001 | D633: Apex Office Solutions | E633: Operations | F633: Office Supplies | G633: ITM002 | H633: Black Toner Cartridge | I633: 14 | J633: 3080.6 | K633: 43128.4 | L633: Net 45 | M633: 45702 | N633: 45700 | O633: West | P633: Ananya Rao | Q633: Closed | R633: On Time
A634: PO202500633 | B634: 46002 | C634: V003 | D634: Prime Workplace India | E634: Operations | F634: Facilities | G634: ITM010 | H634: Printer Maintenance Kit | I634: 5 | J634: 5686.89 | K634: 28434.45 | L634: Net 30 | M634: 46012 | N634: 46011 | O634: South | P634: Ananya Rao | Q634: Closed | R634: On Time
A635: PO202500634 | B635: 45699 | C635: V014 | D635: Insight Advisory Services | E635: IT | F635: Professional Services | G635: ITM020 | H635: Audit Support - Monthly | I635: 3 | J635: 51231.15 | K635: 153693.45 | L635: Net 60 | M635: 45705 | N635: 45703 | O635: North | P635: Vikram Reddy | Q635: Closed | R635: On Time
A636: PO202500635 | B636: 45969 | C636: V005 | D636: Vertex Digital Systems | E636: IT | F636: Technology | G636: ITM006 | H636: Business Laptop - Standard | I636: 6 | J636: 65258.82 | K636: 391552.92 | L636: Net 45 | M636: 45977 | N636: 45976 | O636: South | P636: Vikram Reddy | Q636: Closed | R636: On Time
A637: PO202500636 | B637: 45791 | C637: V012 | D637: BrightReach Media | E637: Sales & Marketing | F637: Marketing | G637: ITM017 | H637: Digital Marketing Campaign | I637: 1 | J637: 42005.01 | K637: 42005.01 | L637: Net 30 | M637: 45797 | N637: 45795 | O637: East | P637: Arjun Nair | Q637: Closed | R637: On Time
A638: PO202500637 | B638: 45815 | C638: V010 | D638: SafeGuard Industrial | E638: Operations | F638: Safety | G638: ITM016 | H638: First Aid Refill Kit | I638: 59 | J638: 2203.58 | K638: 130011.22 | L638: Net 60 | M638: 45833 | N638: 45831 | O638: East | P638: Ananya Rao | Q638: Closed | R638: On Time
...

Sheet Cleaned_Data
A1: PO_Number | B1: PO_Date | C1: Vendor_ID | D1: Vendor_Name | E1: Department | F1: Category | G1: Item_ID | H1: Item_Description | I1: Quantity | J1: Unit_Price_INR | K1: PO_Amount_INR | L1: Payment_Terms | M1: Expected_Delivery_Date | N1: Actual_Delivery_Date | O1: Region | P1: Buyer | Q1: PO_Status | R1: Delivery_Status | S1: Year | T1: Month | U1: Year_Month | V1: Days_Late | W1: On_Time_Flag
A2: PO202500001 | B2: 45772 | C2: V002 | D2: Metro Business Supplies | E2: Finance | F2: Office Supplies | G2: ITM001 | H2: A4 Copier Paper - 500 Sheets | I2: 39 | J2: 232.61 | K2: 9071.79 | L2: Net 30 | M2: 45778 | N2: 45778 | O2: West | P2: Kavya Iyer | Q2: Closed | R2: On Time | S2: 2025 | T2: Apr | U2: 2025-04 | V2: 0 | W2: 1
A3: PO202600002 | B3: 46175 | C3: V002 | D3: Metro Business Supplies | E3: Sales & Marketing | F3: Office Supplies | G3: ITM003 | H3: Ergonomic Office Chair | I3: 8 | J3: 7237.73 | K3: 57901.84 | L3: Net 45 | M3: 46189 | N3: 46189 | O3: West | P3: Ishita Shah | Q3: Closed | R3: On Time | S3: 2026 | T3: Jun | U3: 2026-06 | V3: 0 | W3: 1
A4: PO202500003 | B4: 46006 | C4: V003 | D4: Prime Workplace India | E4: Operations | F4: Facilities | G4: ITM010 | H4: Printer Maintenance Kit | I4: 14 | J4: 5597.17 | K4: 78360.38 | L4: Net 45 | M4: 46016 | N4: 46016 | O4: South | P4: Rohit Mehta | Q4: Closed | R4: On Time | S4: 2025 | T4: Dec | U4: 2025-12 | V4: 0 | W4: 1
A5: PO202500004 | B5: 45738 | C5: V015 | D5: TalentBridge Consulting | E5: IT | F5: Professional Services | G5: ITM020 | H5: Audit Support - Monthly | I5: 1 | J5: 53142.53 | K5: 53142.53 | L5: Net 60 | M5: 45755 | N5: 45755 | O5: South | P5: Vikram Reddy | Q5: Closed | R5: On Time | S5: 2025 | T5: Mar | U5: 2025-03 | V5: 0 | W5: 1
A6: PO202500005 | B6: 45942 | C6: V005 | D6: Vertex Digital Systems | E6: IT | F6: Technology | G6: ITM006 | H6: Business Laptop - Standard | I6: 2 | J6: 64463.55 | K6: 128927.1 | L6: Net 30 | M6: 45956 | N6: 45955 | O6: East | P6: Vikram Reddy | Q6: Closed | R6: On Time | S6: 2025 | T6: Oct | U6: 2025-10 | V6: 0 | W6: 1
A7: PO202500006 | B7: 45715 | C7: V003 | D7: Prime Workplace India | E7: Operations | F7: Facilities | G7: ITM013 | H7: Electrical Maintenance Service | I7: 6 | J7: 19379.08 | K7: 116274.48 | L7: Net 60 | M7: 45723 | N7: 45720 | O7: East | P7: Ananya Rao | Q7: Closed | R7: On Time | S7: 2025 | T7: Feb | U7: 2025-02 | V7: 0 | W7: 1
A8: PO202500007 | B8: 45929 | C8: V016 | D8: StratEdge Partners | E8: IT | F8: Professional Services | G8: ITM022 | H8: Data Reporting Support - Monthly | I8: 1 | J8: 46371.25 | K8: 46371.25 | L8: Net 45 | M8: 45936 | N8: 45936 | O8: South | P8: Vikram Reddy | Q8: Closed | R8: On Time | S8: 2025 | T8: Sep | U8: 2025-09 | V8: 0 | W8: 1
A9: PO202600008 | B9: 46090 | C9: V006 | D9: CoreTech Solutions | E9: Human Resources | F9: Technology | G9: ITM007 | H9: USB-C Docking Station | I9: 14 | J9: 8482.87 | K9: 118760.18 | L9: Net 45 | M9: 46095 | N9: 46095 | O9: North | P9: Neha Kapoor | Q9: Closed | R9: On Time | S9: 2026 | T9: Mar | U9: 2026-03 | V9: 0 | W9: 1
A10: PO202500009 | B10: 45772 | C10: V003 | D10: Prime Workplace India | E10: Operations | F10: Office Supplies | G10: ITM003 | H10: Ergonomic Office Chair | I10: 9 | J10: 8210 | K10: 73890 | L10: Net 60 | M10: 45789 | N10: 45789 | O10: North | P10: Ananya Rao | Q10: Closed | R10: On Time | S10: 2025 | T10: Apr | U10: 2025-04 | V10: 0 | W10: 1
A11: PO202500010 | B11: 45814 | C11: V011 | D11: ProSafe Equipment | E11: Operations | F11: Safety | G11: ITM014 | H11: Safety Gloves - Box | I11: 12 | J11: 686.72 | K11: 8240.64 | L11: Net 30 | M11: 45824 | N11: 45822 | O11: West | P11: Ananya Rao | Q11: Closed | R11: On Time | S11: 2025 | T11: Jun | U11: 2025-06 | V11: 0 | W11: 1
A12: PO202500011 | B12: 45745 | C12: V006 | D12: CoreTech Solutions | E12: IT | F12: Technology | G12: ITM005 | H12: 24-inch Business Monitor | I12: 3 | J12: 10652.85 | K12: 31958.55 | L12: Net 60 | M12: 45754 | N12: 45751 | O12: West | P12: Vikram Reddy | Q12: Closed | R12: On Time | S12: 2025 | T12: Mar | U12: 2025-03 | V12: 0 | W12: 1
A13: PO202600012 | B13: 46040 | C13: V012 | D13: BrightReach Media | E13: Sales & Marketing | F13: Marketing | G13: ITM017 | H13: Digital Marketing Campaign | I13: 3 | J13: 41597.96 | K13: 124793.88 | L13: Net 30 | M13: 46053 | N13: 46052 | O13: South | P13: Arjun Nair | Q13: Closed | R13: On Time | S13: 2026 | T13: Jan | U13: 2026-01 | V13: 0 | W13: 1
... A45: PO202600044 | B45: 46158 | C45: V014 | D45: Insight Advisory Services | E45: Finance | F45: Professional Services | G45: ITM022 | H45: Data Reporting Support - Monthly | I45: 1 | J45: 46154.49 | K45: 46154.49 | L45: Net 30 | M45: 46166 | N45: 46165 | O45: North | P45: Kavya Iyer | Q45: Closed | R45: On Time | S45: 2026 | T45: May | U45: 2026-05 | V45: 0 | W45: 1
A46: PO202600045 | B46: 46201 | C46: V014 | D46: Insight Advisory Services | E46: Administration | F46: Professional Services | G46: ITM021 | H46: Recruitment Service Fee | I46: 1 | J46: 45037.67 | K46: 45037.67 | L46: Net 45 | M46: 46210 | O46: West | P46: Meera Joshi | Q46: Open | R46: Open | S46: 2026 | T46: Jun | U46: 2026-06
A47: PO202500046 | B47: 45941 | C47: V016 | D47: StratEdge Partners | E47: Administration | F47: Professional Services | G47: ITM021 | H47: Recruitment Service Fee | I47: 1 | J47: 45174.98 | K47: 45174.98 | L47: Net 30 | M47: 45949 | N47: 45947 | O47: West | P47: Meera Joshi | Q47: Closed | R47: On Time | S47: 2025 | T47: Oct | U47: 2025-10 | V47: 0 | W47: 1
A48: PO202500047 | B48: 45957 | C48: V009 | D48: Urban Maintenance Co. | E48: Operations | F48: Facilities | G48: ITM010 | H48: Printer Maintenance Kit | I48: 8 | J48: 5244.48 | K48: 41955.84 | L48: Net 60 | M48: 45969 | N48: 45968 | O48: North | P48: Rohit Mehta | Q48: Closed | R48: On Time | S48: 2025 | T48: Oct | U48: 2025-10 | V48: 0 | W48: 1
A49: PO202600048 | B49: 46068 | C49: V001 | D49: Apex Office Solutions | E49: Sales & Marketing | F49: Office Supplies | G49: ITM001 | H49: A4 Copier Paper - 500 Sheets | I49: 24 | J49: 253.09 | K49: 6074.16 | L49: Net 45 | M49: 46074 | N49: 46074 | O49: East | P49: Arjun Nair | Q49: Closed | R49: On Time | S49: 2026 | T49: Feb | U49: 2026-02 | V49: 0 | W49: 1
A50: PO202600049 | B50: 46193 | C50: V003 | D50: Prime Workplace India | E50: Administration | F50: Facilities | G50: ITM013 | H50: Electrical Maintenance Service | I50: 2 | J50: 20109.59 | K50: 40219.18 | L50: Net 30 | M50: 46210 | O50: West | P50: Meera Joshi | Q50: Open | R50: Open | S50: 2026 | T50: Jun | U50: 2026-06
A51: PO202500050 | B51: 45734 | C51: V006 | D51: CoreTech Solutions | E51: Human Resources | F51: Technology | G51: ITM008 | H51: Network Switch - 24 Port | I51: 5 | J51: 14721.39 | K51: 73606.95 | L51: Net 30 | M51: 45750 | N51: 45747 | O51: West | P51: Neha Kapoor | Q51: Closed | R51: On Time | S51: 2025 | T51: Mar | U51: 2025-03 | V51: 0 | W51: 1
A52: PO202500051 | B52: 45860 | C52: V003 | D52: Prime Workplace India | E52: Sales & Marketing | F52: Office Supplies | G52: ITM001 | H52: A4 Copier Paper - 500 Sheets | I52: 9 | J52: 271.17 | K52: 2440.53 | L52: Net 45 | M52: 45865 | N52: 45863 | O52: North | P52: Ishita Shah | Q52: Closed | R52: On Time | S52: 2025 | T52: Jul | U52: 2025-07 | V52: 0 | W52: 1
A53: PO202500052 | B53: 45785 | C53: V015 | D53: TalentBridge Consulting | E53: Finance | F53: Professional Services | G53: ITM021 | H53: Recruitment Service Fee | I53: 1 | J53: 47911.86 | K53: 47911.86 | L53: Net 45 | M53: 45799 | N53: 45807 | O53: North | P53: Kavya Iyer | Q53: Closed | R53: Late | S53: 2025 | T53: May | U53: 2025-05 | V53: 8 | W53: 0
A54: PO202500053 | B54: 45751 | C54: V006 | D54: CoreTech Solutions | E54: IT | F54: Technology | G54: ITM009 | H54: Annual Software License | I54: 3 | J54: 20717.88 | K54: 62153.64 | L54: Net 60 | M54: 45763 | N54: 45760 | O54: West | P54: Vikram Reddy | Q54: Closed | R54: On Time | S54: 2025 | T54: Apr | U54: 2025-04 | V54: 0 | W54: 1
A55: PO202600054 | B55: 46139 | C55: V007 | D55: SecureNet Systems | E55: Finance | F55: Technology | G55: ITM004 | H55: Wireless Keyboard & Mouse | I55: 49 | J55: 1867.53 | K55: 91508.97 | L55: Net 45 | M55: 46151 | N55: 46148 | O55: South | P55: Kavya Iyer | Q55: Closed | R55: On Time | S55: 2026 | T55: Apr | U55: 2026-04 | V55: 0 | W55: 1
A56: PO202500055 | B56: 45748 | C56: V015 | D56: TalentBridge Consulting | E56: Finance | F56: Professional Services | G56: ITM019 | H56: Training Workshop - Per Batch | I56: 2 | J56: 40635.81 | K56: 81271.62 | L56: Net 45 | M56: 45753 | N56: 45751 | O56: East | P56: Kavya Iyer | Q56: Closed | R56: On Time | S56: 2025 | T56: Apr | U56: 2025-04 | V56: 0 | W56: 1
A57: PO202500056 | B57: 45710 | C57: V007 | D57: SecureNet Systems | E57: Sales & Marketing | F57: Technology | G57: ITM007 | H57: USB-C Docking Station | I57: 1 | J57: 9110.9 | K57: 9110.9 | L57: Net 45 | M57: 45725 | N57: 45724 | O57: North | P57: Arjun Nair | Q57: Closed | R57: On Time | S57: 2025 | T57: Feb | U57: 2025-02 | V57: 0 | W57: 1
A58: PO202600057 | B58: 46075 | C58: V003 | D58: Prime Workplace India | E58: Administration | F58: Office Supplies | G58: ITM002 | H58: Black Toner Cartridge | I58: 3 | J58: 3638.09 | K58: 10914.27 | L58: Net 30 | M58: 46087 | N58: 46085 | O58: North | P58: Meera Joshi | Q58: Closed | R58: On Time | S58: 2026 | T58: Feb | U58: 2026-02 | V58: 0 | W58: 1
A59: PO202500058 | B59: 45907 | C59: V002 | D59: Metro Business Supplies | E59: Operations | F59: Office Supplies | G59: ITM003 | H59: Ergonomic Office Chair | I59: 14 | J59: 7537.92 | K59: 105530.88 | L59: Net 30 | M59: 45913 | N59: 45910 | O59: North | P59: Ananya Rao | Q59: Closed | R59: On Time | S59: 2025 | T59: Sep | U59: 2025-09 | V59: 0 | W59: 1
A60: PO202500059 | B60: 45947 | C60: V014 | D60: Insight Advisory Services | E60: IT | F60: Professional Services | G60: ITM020 | H60: Audit Support - Monthly | I60: 1 | J60: 52186.72 | K60: 52186.72 | L60: Net 30 | M60: 45960 | N60: 45957 | O60: North | P60: Vikram Reddy | Q60: Closed | R60: On Time | S60: 2025 | T60: Oct | U60: 2025-10 | V60: 0 | W60: 1
A61: PO202500060 | B61: 45902 | C61: V003 | D61: Prime Workplace India | E61: Operations | F61: Facilities | G61: ITM010 | H61: Printer Maintenance Kit | I61: 15 | J61: 5792.84 | K61: 86892.6 | L61: Net 30 | M61: 45919 | N61: 45918 | O61: South | P61: Ananya Rao | Q61: Closed | R61: On Time | S61: 2025 | T61: Sep | U61: 2025-09 | V61: 0 | W61: 1
A62: PO202600061 | B62: 46108 | C62: V001 | D62: Apex Office Solutions | E62: Administration | F62: Office Supplies | G62: ITM003 | H62: Ergonomic Office Chair | I62: 3 | J62: 8585.36 | K62: 25756.08 | L62: Net 30 | M62: 46114 | N62: 46112 | O62: East | P62: Meera Joshi | Q62: Closed | R62: On Time | S62: 2026 | T62: Mar | U62: 2026-03 | V62: 0 | W62: 1
... A96: PO202500095 | B96: 45948 | C96: V014 | D96: Insight Advisory Services | E96: Administration | F96: Professional Services | G96: ITM020 | H96: Audit Support - Monthly | I96: 1 | J96: 52647.22 | K96: 52647.22 | L96: Net 30 | M96: 45958 | N96: 45955 | O96: South | P96: Meera Joshi | Q96: Closed | R96: On Time | S96: 2025 | T96: Oct | U96: 2025-10 | V96: 0 | W96: 1
A97: PO202600096 | B97: 46197 | C97: V014 | D97: Insight Advisory Services | E97: IT | F97: Professional Services | G97: ITM019 | H97: Training Workshop - Per Batch | I97: 1 | J97: 37096.5 | K97: 37096.5 | L97: Net 60 | M97: 46207 | O97: West | P97: Vikram Reddy | Q97: Open | R97: Open | S97: 2026 | T97: Jun | U97: 2026-06
A98: PO202500097 | B98: 45761 | C98: V001 | D98: Apex Office Solutions | E98: Sales & Marketing | F98: Office Supplies | G98: ITM003 | H98: Ergonomic Office Chair | I98: 13 | J98: 7724.41 | K98: 100417.33 | L98: Net 30 | M98: 45775 | N98: 45772 | O98: West | P98: Arjun Nair | Q98: Closed | R98: On Time | S98: 2025 | T98: Apr | U98: 2025-04 | V98: 0 | W98: 1
A99: PO202600098 | B99: 46106 | C99: V007 | D99: SecureNet Systems | E99: Human Resources | F99: Technology | G99: ITM005 | H99: 24-inch Business Monitor | I99: 8 | J99: 11594.83 | K99: 92758.64 | L99: Net 60 | M99: 46114 | N99: 46112 | O99: East | P99: Neha Kapoor | Q99: Closed | R99: On Time | S99: 2026 | T99: Mar | U99: 2026-03 | V99: 0 | W99: 1
A100: PO202600099 | B100: 46109 | C100: V016 | D100: StratEdge Partners | E100: Finance | F100: Professional Services | G100: ITM022 | H100: Data Reporting Support - Monthly | I100: 3 | J100: 48120.7 | K100: 144362.1 | L100: Net 45 | M100: 46116 | N100: 46116 | O100: North | P100: Kavya Iyer | Q100: Closed | R100: On Time | S100: 2026 | T100: Mar | U100: 2026-03 | V100: 0 | W100: 1
A101: PO202500100 | B101: 45949 | C101: V009 | D101: Urban Maintenance Co. | E101: Operations | F101: Facilities | G101: ITM011 | H101: Cleaning Supplies Kit | I101: 19 | J101: 1254.86 | K101: 23842.34 | L101: Net 60 | M101: 45967 | N101: 45965 | O101: East | P101: Ananya Rao | Q101: Closed | R101: On Time | S101: 2025 | T101: Oct | U101: 2025-10 | V101: 0 | W101: 1
A102: PO202600101 | B102: 46063 | C102: V001 | D102: Apex Office Solutions | E102: Operations | F102: Office Supplies | G102: ITM002 | H102: Black Toner Cartridge | I102: 2 | J102: 3114.35 | K102: 6228.7 | L102: Net 45 | M102: 46081 | N102: 46079 | O102: West | P102: Ananya Rao | Q102: Closed | R102: On Time | S102: 2026 | T102: Feb | U102: 2026-02 | V102: 0 | W102: 1
A103: PO202600102 | B103: 46138 | C103: V001 | D103: Apex Office Solutions | E103: Operations | F103: Office Supplies | G103: ITM001 | H103: A4 Copier Paper - 500 Sheets | I103: 40 | J103: 253.61 | K103: 10144.4 | L103: Net 30 | M103: 46154 | N103: 46151 | O103: North | P103: Ananya Rao | Q103: Closed | R103: On Time | S103: 2026 | T103: Apr | U103: 2026-04 | V103: 0 | W103: 1
A104: PO202500103 | B104: 45966 | C104: V010 | D104: SafeGuard Industrial | E104: Operations | F104: Safety | G104: ITM016 | H104: First Aid Refill Kit | I104: 36 | J104: 2057.32 | K104: 74063.52 | L104: Net 45 | M104: 45980 | N104: 45979 | O104: North | P104: Rohit Mehta | Q104: Closed | R104: On Time | S104: 2025 | T104: Nov | U104: 2025-11 | V104: 0 | W104: 1
A105: PO202500104 | B105: 45659 | C105: V015 | D105: TalentBridge Consulting | E105: Finance | F105: Professional Services | G105: ITM020 | H105: Audit Support - Monthly | I105: 1 | J105: 53339.91 | K105: 53339.91 | L105: Net 30 | M105: 45665 | N105: 45665 | O105: East | P105: Kavya Iyer | Q105: Closed | R105: On Time | S105: 2025 | T105: Jan | U105: 2025-01 | V105: 0 | W105: 1
A106: PO202500105 | B106: 46011 | C106: V006 | D106: CoreTech Solutions | E106: IT | F106: Technology | G106: ITM008 | H106: Network Switch - 24 Port | I106: 1 | J106: 15134 | K106: 15134 | L106: Net 45 | M106: 46021 | N106: 46020 | O106: East | P106: Vikram Reddy | Q106: Closed | R106: On Time | S106: 2025 | T106: Dec | U106: 2025-12 | V106: 0 | W106: 1
A107: PO202500106 | B107: 45722 | C107: V001 | D107: Apex Office Solutions | E107: Administration | F107: Office Supplies | G107: ITM002 | H107: Black Toner Cartridge | I107: 15 | J107: 3443.18 | K107: 51647.7 | L107: Net 30 | M107: 45727 | N107: 45725 | O107: East | P107: Meera Joshi | Q107: Closed | R107: On Time | S107: 2025 | T107: Mar | U107: 2025-03 | V107: 0 | W107: 1
A108: PO202500107 | B108: 45853 | C108: V001 | D108: Apex Office Solutions | E108: Administration | F108: Office Supplies | G108: ITM003 | H108: Ergonomic Office Chair | I108: 6 | J108: 8029.9 | K108: 48179.4 | L108: Net 60 | M108: 45864 | N108: 45861 | O108: East | P108: Meera Joshi | Q108: Closed | R108: On Time | S108: 2025 | T108: Jul | U108: 2025-07 | V108: 0 | W108: 1
A109: PO202500108 | B109: 45849 | C109: V003 | D109: Prime Workplace India | E109: Sales & Marketing | F109: Office Supplies | G109: ITM002 | H109: Black Toner Cartridge | I109: 2 | J109: 3456.24 | K109: 6912.48 | L109: Net 30 | M109: 45860 | N109: 45859 | O109: North | P109: Arjun Nair | Q109: Closed | R109: On Time | S109: 2025 | T109: Jul | U109: 2025-07 | V109: 0 | W109: 1
... A263: PO202500262 | B263: 45997 | C263: V006 | D263: CoreTech Solutions | E263: Sales & Marketing | F263: Technology | G263: ITM009 | H263: Annual Software License | I263: 2 | J263: 20975.25 | K263: 41950.5 | L263: Net 30 | M263: 46003 | N263: 46002 | O263: North | P263: Ishita Shah | Q263: Closed | R263: On Time | S263: 2025 | T263: Dec | U263: 2025-12 | V263: 0 | W263: 1
A264: PO202600263 | B264: 46192 | C264: V001 | D264: Apex Office Solutions | E264: Operations | F264: Office Supplies | G264: ITM002 | H264: Black Toner Cartridge | I264: 12 | J264: 3227.23 | K264: 38726.76 | L264: Net 60 | M264: 46203 | O264: East | P264: Ananya Rao | Q264: Open | R264: Open | S264: 2026 | T264: Jun | U264: 2026-06
A265: PO202600264 | B265: 46119 | C265: V003 | D265: Prime Workplace India | E265: Sales & Marketing | F265: Office Supplies | G265: ITM001 | H265: A4 Copier Paper - 500 Sheets | I265: 52 | J265: 251.77 | K265: 13092.04 | L265: Net 45 | M265: 46124 | N265: 46121 | O265: East | P265: Arjun Nair | Q265: Closed | R265: On Time | S265: 2026 | T265: Apr | U265: 2026-04 | V265: 0 | W265: 1
A266: PO202500265 | B266: 45789 | C266: V014 | D266: Insight Advisory Services | E266: IT | F266: Professional Services | G266: ITM022 | H266: Data Reporting Support - Monthly | I266: 1 | J266: 48710.85 | K266: 48710.85 | L266: Net 60 | M266: 45798 | N266: 45796 | O266: East | P266: Vikram Reddy | Q266: Closed | R266: On Time | S266: 2025 | T266: May | U266: 2025-05 | V266: 0 | W266: 1
A267: PO202500266 | B267: 45799 | C267: V015 | D267: TalentBridge Consulting | E267: IT | F267: Professional Services | G267: ITM021 | H267: Recruitment Service Fee | I267: 1 | J267: 49808.15 | K267: 49808.15 | L267: Net 45 | M267: 45807 | N267: 45805 | O267: West | P267: Vikram Reddy | Q267: Closed | R267: On Time | S267: 2025 | T267: May | U267: 2025-05 | V267: 0 | W267: 1
A268: PO202600267 | B268: 46173 | C268: V002 | D268: Metro Business Supplies | E268: Sales & Marketing | F268: Office Supplies | G268: ITM001 | H268: A4 Copier Paper - 500 Sheets | I268: 42 | J268: 230.27 | K268: 9671.34 | L268: Net 45 | M268: 46187 | N268: 46184 | O268: North | P268: Ishita Shah | Q268: Closed | R268: On Time | S268: 2026 | T268: May | U268: 2026-05 | V268: 0 | W268: 1
A269: PO202500268 | B269: 45671 | C269: V002 | D269: Metro Business Supplies | E269: Operations | F269: Office Supplies | G269: ITM001 | H269: A4 Copier Paper - 500 Sheets | I269: 53 | J269: 222.84 | K269: 11810.52 | L269: Net 45 | M269: 45688 | N269: 45694 | O269: West | P269: Ananya Rao | Q269: Closed | R269: Late | S269: 2025 | T269: Jan | U269: 2025-01 | V269: 6 | W269: 0
A270: PO202500269 | B270: 45960 | C270: V004 | D270: Nexa Technologies | E270: Sales & Marketing | F270: Technology | G270: ITM007 | H270: USB-C Docking Station | I270: 12 | J270: 9054.51 | K270: 108654.12 | L270: Net 30 | M270: 45973 | N270: 45970 | O270: North | P270: Arjun Nair | Q270: Closed | R270: On Time | S270: 2025 | T270: Oct | U270: 2025-10 | V270: 0 | W270: 1
A271: PO202600270 | B271: 46048 | C271: V016 | D271: StratEdge Partners | E271: Administration | F271: Professional Services | G271: ITM021 | H271: Recruitment Service Fee | I271: 1 | J271: 42115.36 | K271: 42115.36 | L271: Net 45 | M271: 46056 | N271: 46053 | O271: North | P271: Meera Joshi | Q271: Closed | R271: On Time | S271: 2026 | T271: Jan | U271: 2026-01 | V271: 0 | W271: 1
A272: PO202500271 | B272: 45856 | C272: V010 | D272: SafeGuard Industrial | E272: Operations | F272: Safety | G272: ITM014 | H272: Safety Gloves - Box | I272: 37 | J272: 709.49 | K272: 26251.13 | L272: Net 30 | M272: 45862 | N272: 45859 | O272: North | P272: Ananya Rao | Q272: Closed | R272: On Time | S272: 2025 | T272: Jul | U272: 2025-07 | V272: 0 | W272: 1
A273: PO202500272 | B273: 45822 | C273: V015 | D273: TalentBridge Consulting | E273: Finance | F273: Professional Services | G273: ITM022 | H273: Data Reporting Support - Monthly | I273: 1 | J273: 49553.69 | K273: 49553.69 | L273: Net 30 | M273: 45832 | N273: 45830 | O273: North | P273: Kavya Iyer | Q273: Closed | R273: On Time | S273: 2025 | T273: Jun | U273: 2025-06 | V273: 0 | W273: 1
A274: PO202500273 | B274: 45983 | C274: V016 | D274: StratEdge Partners | E274: Administration | F274: Professional Services | G274: ITM019 | H274: Training Workshop - Per Batch | I274: 3 | J274: 35914.3 | K274: 107742.9 | L274: Net 30 | M274: 45996 | N274: 45994 | O274: West | P274: Meera Joshi | Q274: Closed | R274: On Time | S274: 2025 | T274: Nov | U274: 2025-11 | V274: 0 | W274: 1
A275: PO202500274 | B275: 45997 | C275: V010 | D275: SafeGuard Industrial | E275: Operations | F275: Safety | G275: ITM016 | H275: First Aid Refill Kit | I275: 53 | J275: 2143.31 | K275: 113595.43 | L275: Net 30 | M275: 46012 | N275: 46024 | O275: West | P275: Ananya Rao | Q275: Closed | R275: Late | S275: 2025 | T275: Dec | U275: 2025-12 | V275: 12 | W275: 0
A276: PO202500275 | B276: 45986 | C276: V005 | D276: Vertex Digital Systems | E276: IT | F276: Technology | G276: ITM007 | H276: USB-C Docking Station | I276: 1 | J276: 9853.82 | K276: 9853.82 | L276: Net 30 | M276: 45999 | N276: 45997 | O276: East | P276: Vikram Reddy | Q276: Closed | R276: On Time | S276: 2025 | T276: Nov | U276: 2025-11 | V276: 0 | W276: 1
... A298: PO202600297 | B298: 46048 | C298: V004 | D298: Nexa Technologies | E298: IT | F298: Technology | G298: ITM007 | H298: USB-C Docking Station | I298: 4 | J298: 8747.67 | K298: 34990.68 | L298: Net 30 | M298: 46066 | N298: 46063 | O298: South | P298: Vikram Reddy | Q298: Closed | R298: On Time | S298: 2026 | T298: Jan | U298: 2026-01 | V298: 0 | W298: 1
A299: PO202600298 | B299: 46193 | C299: V011 | D299: ProSafe Equipment | E299: Operations | F299: Safety | G299: ITM014 | H299: Safety Gloves - Box | I299: 28 | J299: 676.09 | K299: 18930.52 | L299: Net 30 | M299: 46199 | O299: North | P299: Rohit Mehta | Q299: Open | R299: Open | S299: 2026 | T299: Jun | U299: 2026-06
A300: PO202600299 | B300: 46081 | C300: V013 | D300: MarketCraft Communications | E300: Sales & Marketing | F300: Marketing | G300: ITM018 | H300: Printed Marketing Materials | I300: 1 | J300: 13798.65 | K300: 13798.65 | L300: Net 45 | M300: 46095 | N300: 46092 | O300: South | P300: Arjun Nair | Q300: Closed | R300: On Time | S300: 2026 | T300: Feb | U300: 2026-02 | V300: 0 | W300: 1
A301: PO202500300 | B301: 45823 | C301: V006 | D301: CoreTech Solutions | E301: Sales & Marketing | F301: Technology | G301: ITM008 | H301: Network Switch - 24 Port | I301: 1 | J301: 15618.39 | K301: 15618.39 | L301: Net 45 | M301: 45830 | N301: 45830 | O301: West | P301: Ishita Shah | Q301: Closed | R301: On Time | S301: 2025 | T301: Jun | U301: 2025-06 | V301: 0 | W301: 1
A302: PO202600301 | B302: 46103 | C302: V015 | D302: TalentBridge Consulting | E302: Finance | F302: Professional Services | G302: ITM019 | H302: Training Workshop - Per Batch | I302: 2 | J302: 41295.24 | K302: 82590.48 | L302: Net 45 | M302: 46117 | N302: 46115 | O302: South | P302: Kavya Iyer | Q302: Closed | R302: On Time | S302: 2026 | T302: Mar | U302: 2026-03 | V302: 0 | W302: 1
A303: PO202600302 | B303: 46164 | C303: V010 | D303: SafeGuard Industrial | E303: Operations | F303: Safety | G303: ITM016 | H303: First Aid Refill Kit | I303: 43 | J303: 2042.58 | K303: 87830.94 | L303: Net 45 | M303: 46177 | N303: 46176 | O303: South | P303: Rohit Mehta | Q303: Closed | R303: On Time | S303: 2026 | T303: May | U303: 2026-05 | V303: 0 | W303: 1
A304: PO202500303 | B304: 45819 | C304: V015 | D304: TalentBridge Consulting | E304: Finance | F304: Professional Services | G304: ITM021 | H304: Recruitment Service Fee | I304: 1 | J304: 47532.6 | K304: 47532.6 | L304: Net 30 | M304: 45832 | N304: 45845 | O304: South | P304: Kavya Iyer | Q304: Closed | R304: Late | S304: 2025 | T304: Jun | U304: 2025-06 | V304: 13 | W304: 0
A305: PO202500304 | B305: 46014 | C305: V007 | D305: SecureNet Systems | E305: IT | F305: Technology | G305: ITM008 | H305: Network Switch - 24 Port | I305: 7 | J305: 17151.91 | K305: 120063.37 | L305: Net 30 | M305: 46028 | N305: 46032 | O305: South | P305: Vikram Reddy | Q305: Closed | R305: Late | S305: 2025 | T305: Dec | U305: 2025-12 | V305: 4 | W305: 0
A306: PO202600305 | B306: 46173 | C306: V016 | D306: StratEdge Partners | E306: Administration | F306: Professional Services | G306: ITM021 | H306: Recruitment Service Fee | I306: 3 | J306: 45098.45 | K306: 135295.35 | L306: Net 45 | M306: 46182 | N306: 46179 | O306: West | P306: Meera Joshi | Q306: Closed | R306: On Time | S306: 2026 | T306: May | U306: 2026-05 | V306: 0 | W306: 1
A307: PO202500306 | B307: 45686 | C307: V015 | D307: TalentBridge Consulting | E307: Finance | F307: Professional Services | G307: ITM020 | H307: Audit Support - Monthly | I307: 1 | J307: 54055.84 | K307: 54055.84 | L307: Net 45 | M307: 45697 | N307: 45697 | O307: North | P307: Kavya Iyer | Q307: Closed | R307: On Time | S307: 2025 | T307: Jan | U307: 2025-01 | V307: 0 | W307: 1
A308: PO202500307 | B308: 45952 | C308: V015 | D308: TalentBridge Consulting | E308: IT | F308: Professional Services | G308: ITM019 | H308: Training Workshop - Per Batch | I308: 1 | J308: 39315.85 | K308: 39315.85 | L308: Net 30 | M308: 45962 | N308: 45960 | O308: West | P308: Vikram Reddy | Q308: Closed | R308: On Time | S308: 2025 | T308: Oct | U308: 2025-10 | V308: 0 | W308: 1
A309: PO202500308 | B309: 45862 | C309: V014 | D309: Insight Advisory Services | E309: Finance | F309: Professional Services | G309: ITM020 | H309: Audit Support - Monthly | I309: 3 | J309: 53827.52 | K309: 161482.56 | L309: Net 30 | M309: 45872 | N309: 45872 | O309: South | P309: Kavya Iyer | Q309: Closed | R309: On Time | S309: 2025 | T309: Jul | U309: 2025-07 | V309: 0 | W309: 1
A310: PO202600309 | B310: 46038 | C310: V002 | D310: Metro Business Supplies | E310: Sales & Marketing | F310: Office Supplies | G310: ITM002 | H310: Black Toner Cartridge | I310: 15 | J310: 3071.86 | K310: 46077.9 | L310: Net 45 | M310: 46051 | N310: 46050 | O310: West | P310: Arjun Nair | Q310: Closed | R310: On Time | S310: 2026 | T310: Jan | U310: 2026-01 | V310: 0 | W310: 1
A311: PO202500310 | B311: 45691 | C311: V006 | D311: CoreTech Solutions | E311: Human Resources | F311: Technology | G311: ITM005 | H311: 24-inch Business Monitor | I311: 8 | J311: 9894.73 | K311: 79157.84 | L311: Net 45 | M311: 45701 | N311: 45701 | O311: East | P311: Neha Kapoor | Q311: Closed | R311: On Time | S311: 2025 | T311: Feb | U311: 2025-02 | V311: 0 | W311: 1
... A350: PO202600349 | B350: 46118 | C350: V004 | D350: Nexa Technologies | E350: Finance | F350: Technology | G350: ITM008 | H350: Network Switch - 24 Port | I350: 5 | J350: 16615.11 | K350: 83075.55 | L350: Net 45 | M350: 46131 | N350: 46130 | O350: South | P350: Kavya Iyer | Q350: Closed | R350: On Time | S350: 2026 | T350: Apr | U350: 2026-04 | V350: 0 | W350: 1
A351: PO202600350 | B351: 46197 | C351: V009 | D351: Urban Maintenance Co. | E351: Operations | F351: Facilities | G351: ITM011 | H351: Cleaning Supplies Kit | I351: 8 | J351: 1316.24 | K351: 10529.92 | L351: Net 45 | M351: 46209 | O351: North | P351: Ananya Rao | Q351: Open | R351: Open | S351: 2026 | T351: Jun | U351: 2026-06
A352: PO202500351 | B352: 45677 | C352: V009 | D352: Urban Maintenance Co. | E352: Administration | F352: Facilities | G352: ITM011 | H352: Cleaning Supplies Kit | I352: 50 | J352: 1303.48 | K352: 65174 | L352: Net 60 | M352: 45683 | N352: 45680 | O352: South | P352: Meera Joshi | Q352: Closed | R352: On Time | S352: 2025 | T352: Jan | U352: 2025-01 | V352: 0 | W352: 1
A353: PO202500352 | B353: 45861 | C353: V004 | D353: Nexa Technologies | E353: Human Resources | F353: Technology | G353: ITM004 | H353: Wireless Keyboard & Mouse | I353: 24 | J353: 1890.97 | K353: 45383.28 | L353: Net 30 | M353: 45871 | N353: 45870 | O353: North | P353: Neha Kapoor | Q353: Closed | R353: On Time | S353: 2025 | T353: Jul | U353: 2025-07 | V353: 0 | W353: 1
A354: PO202500353 | B354: 45967 | C354: V016 | D354: StratEdge Partners | E354: Administration | F354: Professional Services | G354: ITM021 | H354: Recruitment Service Fee | I354: 2 | J354: 44362.43 | K354: 88724.86 | L354: Net 30 | M354: 45985 | N354: 45983 | O354: North | P354: Meera Joshi | Q354: Closed | R354: On Time | S354: 2025 | T354: Nov | U354: 2025-11 | V354: 0 | W354: 1
A355: PO202500354 | B355: 45798 | C355: V007 | D355: SecureNet Systems | E355: Human Resources | F355: Technology | G355: ITM008 | H355: Network Switch - 24 Port | I355: 7 | J355: 17509.34 | K355: 122565.38 | L355: Net 60 | M355: 45806 | N355: 45803 | O355: North | P355: Neha Kapoor | Q355: Closed | R355: On Time | S355: 2025 | T355: May | U355: 2025-05 | V355: 0 | W355: 1
A356: PO202500355 | B356: 45792 | C356: V011 | D356: ProSafe Equipment | E356: Operations | F356: Safety | G356: ITM016 | H356: First Aid Refill Kit | I356: 24 | J356: 2070.08 | K356: 49681.92 | L356: Net 30 | M356: 45808 | N356: 45807 | O356: West | P356: Ananya Rao | Q356: Closed | R356: On Time | S356: 2025 | T356: May | U356: 2025-05 | V356: 0 | W356: 1
A357: PO202500356 | B357: 45983 | C357: V001 | D357: Apex Office Solutions | E357: Sales & Marketing | F357: Office Supplies | G357: ITM001 | H357: A4 Copier Paper - 500 Sheets | I357: 14 | J357: 253.71 | K357: 3551.94 | L357: Net 60 | M357: 45999 | N357: 46006 | O357: East | P357: Ishita Shah | Q357: Closed | R357: Late | S357: 2025 | T357: Nov | U357: 2025-11 | V357: 7 | W357: 0
A358: PO202500357 | B358: 45968 | C358: V014 | D358: Insight Advisory Services | E358: Administration | F358: Professional Services | G358: ITM021 | H358: Recruitment Service Fee | I358: 1 | J358: 43961.13 | K358: 43961.13 | L358: Net 45 | M358: 45975 | N358: 45986 | O358: West | P358: Meera Joshi | Q358: Closed | R358: Late | S358: 2025 | T358: Nov | U358: 2025-11 | V358: 11 | W358: 0
A359: PO202600358 | B359: 46025 | C359: V006 | D359: CoreTech Solutions | E359: IT | F359: Technology | G359: ITM008 | H359: Network Switch - 24 Port | I359: 6 | J359: 15321.46 | K359: 91928.76 | L359: Net 30 | M359: 46032 | N359: 46029 | O359: West | P359: Vikram Reddy | Q359: Closed | R359: On Time | S359: 2026 | T359: Jan | U359: 2026-01 | V359: 0 | W359: 1
A360: PO202500359 | B360: 45889 | C360: V007 | D360: SecureNet Systems | E360: IT | F360: Technology | G360: ITM006 | H360: Business Laptop - Standard | I360: 4 | J360: 58478.38 | K360: 233913.52 | L360: Net 60 | M360: 45906 | N360: 45905 | O360: East | P360: Vikram Reddy | Q360: Closed | R360: On Time | S360: 2025 | T360: Aug | U360: 2025-08 | V360: 0 | W360: 1
A361: PO202500360 | B361: 45910 | C361: V014 | D361: Insight Advisory Services | E361: IT | F361: Professional Services | G361: ITM021 | H361: Recruitment Service Fee | I361: 3 | J361: 47003.51 | K361: 141010.53 | L361: Net 30 | M361: 45924 | N361: 45924 | O361: East | P361: Vikram Reddy | Q361: Closed | R361: On Time | S361: 2025 | T361: Sep | U361: 2025-09 | V361: 0 | W361: 1
A362: PO202500361 | B362: 45909 | C362: V006 | D362: CoreTech Solutions | E362: Human Resources | F362: Technology | G362: ITM004 | H362: Wireless Keyboard & Mouse | I362: 45 | J362: 1694.36 | K362: 76246.2 | L362: Net 30 | M362: 45914 | N362: 45923 | O362: North | P362: Neha Kapoor | Q362: Closed | R362: Late | S362: 2025 | T362: Sep | U362: 2025-09 | V362: 9 | W362: 0
A363: PO202600362 | B363: 46130 | C363: V002 | D363: Metro Business Supplies | E363: Finance | F363: Office Supplies | G363: ITM003 | H363: Ergonomic Office Chair | I363: 14 | J363: 7056.7 | K363: 98793.8 | L363: Net 30 | M363: 46145 | N363: 46145 | O363: West | P363: Kavya Iyer | Q363: Closed | R363: On Time | S363: 2026 | T363: Apr | U363: 2026-04 | V363: 0 | W363: 1
... A626: PO202500625 | B626: 46022 | C626: V014 | D626: Insight Advisory Services | E626: Human Resources | F626: Professional Services | G626: ITM021 | H626: Recruitment Service Fee | I626: 1 | J626: 44616.37 | K626: 44616.37 | L626: Net 30 | M626: 46033 | N626: 46033 | O626: West | P626: Neha Kapoor | Q626: Closed | R626: On Time | S626: 2025 | T626: Dec | U626: 2025-12 | V626: 0 | W626: 1
A627: PO202600626 | B627: 46199 | C627: V001 | D627: Apex Office Solutions | E627: Operations | F627: Office Supplies | G627: ITM002 | H627: Black Toner Cartridge | I627: 5 | J627: 3242.14 | K627: 16210.7 | L627: Net 30 | M627: 46207 | O627: West | P627: Rohit Mehta | Q627: Open | R627: Open | S627: 2026 | T627: Jun | U627: 2026-06
A628: PO202600627 | B628: 46107 | C628: V014 | D628: Insight Advisory Services | E628: Finance | F628: Professional Services | G628: ITM019 | H628: Training Workshop - Per Batch | I628: 1 | J628: 39457.16 | K628: 39457.16 | L628: Net 30 | M628: 46113 | N628: 46113 | O628: East | P628: Kavya Iyer | Q628: Closed | R628: On Time | S628: 2026 | T628: Mar | U628: 2026-03 | V628: 0 | W628: 1
A629: PO202500628 | B629: 45690 | C629: V003 | D629: Prime Workplace India | E629: Operations | F629: Facilities | G629: ITM012 | H629: LED Panel Light | I629: 36 | J629: 1772.59 | K629: 63813.24 | L629: Net 30 | M629: 45707 | N629: 45706 | O629: East | P629: Rohit Mehta | Q629: Closed | R629: On Time | S629: 2025 | T629: Feb | U629: 2025-02 | V629: 0 | W629: 1
A630: PO202500629 | B630: 45792 | C630: V001 | D630: Apex Office Solutions | E630: Operations | F630: Office Supplies | G630: ITM001 | H630: A4 Copier Paper - 500 Sheets | I630: 54 | J630: 246.23 | K630: 13296.42 | L630: Net 30 | M630: 45807 | N630: 45805 | O630: South | P630: Rohit Mehta | Q630: Closed | R630: On Time | S630: 2025 | T630: May | U630: 2025-05 | V630: 0 | W630: 1
A631: PO202600630 | B631: 46149 | C631: V006 | D631: CoreTech Solutions | E631: Sales & Marketing | F631: Technology | G631: ITM005 | H631: 24-inch Business Monitor | I631: 3 | J631: 10453.25 | K631: 31359.75 | L631: Net 60 | M631: 46157 | N631: 46157 | O631: West | P631: Ishita Shah | Q631: Closed | R631: On Time | S631: 2026 | T631: May | U631: 2026-05 | V631: 0 | W631: 1
A632: PO202500631 | B632: 45861 | C632: V006 | D632: CoreTech Solutions | E632: IT | F632: Technology | G632: ITM009 | H632: Annual Software License | I632: 4 | J632: 20782.11 | K632: 83128.44 | L632: Net 30 | M632: 45879 | N632: 45878 | O632: West | P632: Vikram Reddy | Q632: Closed | R632: On Time | S632: 2025 | T632: Jul | U632: 2025-07 | V632: 0 | W632: 1
A633: PO202500632 | B633: 45697 | C633: V001 | D633: Apex Office Solutions | E633: Operations | F633: Office Supplies | G633: ITM002 | H633: Black Toner Cartridge | I633: 14 | J633: 3080.6 | K633: 43128.4 | L633: Net 45 | M633: 45702 | N633: 45700 | O633: West | P633: Ananya Rao | Q633: Closed | R633: On Time | S633: 2025 | T633: Feb | U633: 2025-02 | V633: 0 | W633: 1
A634: PO202500633 | B634: 46002 | C634: V003 | D634: Prime Workplace India | E634: Operations | F634: Facilities | G634: ITM010 | H634: Printer Maintenance Kit | I634: 5 | J634: 5686.89 | K634: 28434.45 | L634: Net 30 | M634: 46012 | N634: 46011 | O634: South | P634: Ananya Rao | Q634: Closed | R634: On Time | S634: 2025 | T634: Dec | U634: 2025-12 | V634: 0 | W634: 1
A635: PO202500634 | B635: 45699 | C635: V014 | D635: Insight Advisory Services | E635: IT | F635: Professional Services | G635: ITM020 | H635: Audit Support - Monthly | I635: 3 | J635: 51231.15 | K635: 153693.45 | L635: Net 60 | M635: 45705 | N635: 45703 | O635: North | P635: Vikram Reddy | Q635: Closed | R635: On Time | S635: 2025 | T635: Feb | U635: 2025-02 | V635: 0 | W635: 1
A636: PO202500635 | B636: 45969 | C636: V005 | D636: Vertex Digital Systems | E636: IT | F636: Technology | G636: ITM006 | H636: Business Laptop - Standard | I636: 6 | J636: 65258.82 | K636: 391552.92 | L636: Net 45 | M636: 45977 | N636: 45976 | O636: South | P636: Vikram Reddy | Q636: Closed | R636: On Time | S636: 2025 | T636: Nov | U636: 2025-11 | V636: 0 | W636: 1
A637: PO202500636 | B637: 45791 | C637: V012 | D637: BrightReach Media | E637: Sales & Marketing | F637: Marketing | G637: ITM017 | H637: Digital Marketing Campaign | I637: 1 | J637: 42005.01 | K637: 42005.01 | L637: Net 30 | M637: 45797 | N637: 45795 | O637: East | P637: Arjun Nair | Q637: Closed | R637: On Time | S637: 2025 | T637: May | U637: 2025-05 | V637: 0 | W637: 1
A638: PO202500637 | B638: 45815 | C638: V010 | D638: SafeGuard Industrial | E638: Operations | F638: Safety | G638: ITM016 | H638: First Aid Refill Kit | I638: 59 | J638: 2203.58 | K638: 130011.22 | L638: Net 60 | M638: 45833 | N638: 45831 | O638: East | P638: Ananya Rao | Q638: Closed | R638: On Time | S638: 2025 | T638: Jun | U638: 2025-06 | V638: 0 | W638: 1
...

Sheet Excel_Analysis
A1: Excel Analysis
A3: Total Spend | B3: Total POs | C3: Average PO Value | D3: On-Time Delivery % | E3: Late POs | F3: Top 3 Vendor Share
A4: =SUM(Cleaned_Data!$K$2:$K$2601) -> 1.5786407e+08 | B4: =COUNTA(Cleaned_Data!$A$2:$A$2601) -> 2600 | C4: =A4/B4 -> 60716.949 | D4: =COUNTIF(Cleaned_Data!$R$2:$R$2601,"On Time")/(COUNTIF(Cleaned_Data!$R$2:$R$2601,"On Time")+COUNTIF(Cleaned_Data!$R$2:$R$2601,"Late")) -> 0.9024485 | E4: =COUNTIF(Cleaned_Data!$R$2:$R$2601,"Late") -> 251 | F4: =SUM(J8:J10)/A4 -> 0.3709861
A7: Year_Month | B7: Spend_INR | C7: PO_Count | I7: Vendor | J7: Spend_INR | K7: Spend_Share | L7: Closed_POs | M7: Late_POs | N7: On_Time_%
A8: 2025-01 | B8: =SUMIF(Cleaned_Data!$U$2:$U$2601,A8,Cleaned_Data!$K$2:$K$2601) -> 8281696.5 | C8: =COUNTIF(Cleaned_Data!$U$2:$U$2601,A8) -> 140 | I8: CoreTech Solutions | J8: =SUMIF(Cleaned_Data!$D$2:$D$2601,I8,Cleaned_Data!$K$2:$K$2601) -> 25491861 | K8: =J8/$A$4 -> 0.16147982 | L8: =COUNTIFS(Cleaned_Data!$D$2:$D$2601,I8,Cleaned_Data!$Q$2:$Q$2601,"Closed") -> 294 | M8: =COUNTIFS(Cleaned_Data!$D$2:$D$2601,I8,Cleaned_Data!$R$2:$R$2601,"Late") -> 66 | N8: =IF(L8=0,0,(L8-M8)/L8) -> 0.7755102
A9: 2025-02 | B9: =SUMIF(Cleaned_Data!$U$2:$U$2601,A9,Cleaned_Data!$K$2:$K$2601) -> 6915595.3 | C9: =COUNTIF(Cleaned_Data!$U$2:$U$2601,A9) -> 119 | I9: Insight Advisory Services | J9: =SUMIF(Cleaned_Data!$D$2:$D$2601,I9,Cleaned_Data!$K$2:$K$2601) -> 20279626 | K9: =J9/$A$4 -> 0.12846258 | L9: =COUNTIFS(Cleaned_Data!$D$2:$D$2601,I9,Cleaned_Data!$Q$2:$Q$2601,"Closed") -> 277 | M9: =COUNTIFS(Cleaned_Data!$D$2:$D$2601,I9,Cleaned_Data!$R$2:$R$2601,"Late") -> 17 | N9: =IF(L9=0,0,(L9-M9)/L9) -> 0.93862816
A10: 2025-03 | B10: =SUMIF(Cleaned_Data!$U$2:$U$2601,A10,Cleaned_Data!$K$2:$K$2601) -> 10956499 | C10: =COUNTIF(Cleaned_Data!$U$2:$U$2601,A10) -> 179 | I10: Prime Workplace India | J10: =SUMIF(Cleaned_Data!$D$2:$D$2601,I10,Cleaned_Data!$K$2:$K$2601) -> 12793887 | K10: =J10/$A$4 -> 0.081043695 | L10: =COUNTIFS(Cleaned_Data!$D$2:$D$2601,I10,Cleaned_Data!$Q$2:$Q$2601,"Closed") -> 280 | M10: =COUNTIFS(Cleaned_Data!$D$2:$D$2601,I10,Cleaned_Data!$R$2:$R$2601,"Late") -> 11 | N10: =IF(L10=0,0,(L10-M10)/L10) -> 0.96071429
A11: 2025-04 | B11: =SUMIF(Cleaned_Data!$U$2:$U$2601,A11,Cleaned_Data!$K$2:$K$2601) -> 7751137.7 | C11: =COUNTIF(Cleaned_Data!$U$2:$U$2601,A11) -> 129 | I11: Nexa Technologies | J11: =SUMIF(Cleaned_Data!$D$2:$D$2601,I11,Cleaned_Data!$K$2:$K$2601) -> 12263850 | K11: =J11/$A$4 -> 0.077686138 | L11: =COUNTIFS(Cleaned_Data!$D$2:$D$2601,I11,Cleaned_Data!$Q$2:$Q$2601,"Closed") -> 123 | M11: =COUNTIFS(Cleaned_Data!$D$2:$D$2601,I11,Cleaned_Data!$R$2:$R$2601,"Late") -> 14 | N11: =IF(L11=0,0,(L11-M11)/L11) -> 0.88617886
A12: 2025-05 | B12: =SUMIF(Cleaned_Data!$U$2:$U$2601,A12,Cleaned_Data!$K$2:$K$2601) -> 9736517 | C12: =COUNTIF(Cleaned_Data!$U$2:$U$2601,A12) -> 144 | I12: Apex Office Solutions | J12: =SUMIF(Cleaned_Data!$D$2:$D$2601,I12,Cleaned_Data!$K$2:$K$2601) -> 12072508 | K12: =J12/$A$4 -> 0.076474074 | L12: =COUNTIFS(Cleaned_Data!$D$2:$D$2601,I12,Cleaned_Data!$Q$2:$Q$2601,"Closed") -> 354 | M12: =COUNTIFS(Cleaned_Data!$D$2:$D$2601,I12,Cleaned_Data!$R$2:$R$2601,"Late") -> 25 | N12: =IF(L12=0,0,(L12-M12)/L12) -> 0.92937853
A13: 2025-06 | B13: =SUMIF(Cleaned_Data!$U$2:$U$2601,A13,Cleaned_Data!$K$2:$K$2601) -> 8315221 | C13: =COUNTIF(Cleaned_Data!$U$2:$U$2601,A13) -> 140 | I13: TalentBridge Consulting | J13: =SUMIF(Cleaned_Data!$D$2:$D$2601,I13,Cleaned_Data!$K$2:$K$2601) -> 11774497 | K13: =J13/$A$4 -> 0.074586299 | L13: =COUNTIFS(Cleaned_Data!$D$2:$D$2601,I13,Cleaned_Data!$Q$2:$Q$2601,"Closed") -> 150 | M13: =COUNTIFS(Cleaned_Data!$D$2:$D$2601,I13,Cleaned_Data!$R$2:$R$2601,"Late") -> 7 | N13: =IF(L13=0,0,(L13-M13)/L13) -> 0.95333333
A14: 2025-07 | B14: =SUMIF(Cleaned_Data!$U$2:$U$2601,A14,Cleaned_Data!$K$2:$K$2601) -> 7115578.2 | C14: =COUNTIF(Cleaned_Data!$U$2:$U$2601,A14) -> 127 | I14: SecureNet Systems | J14: =SUMIF(Cleaned_Data!$D$2:$D$2601,I14,Cleaned_Data!$K$2:$K$2601) -> 11127772 | K14: =J14/$A$4 -> 0.070489579 | L14: =COUNTIFS(Cleaned_Data!$D$2:$D$2601,I14,Cleaned_Data!$Q$2:$Q$2601,"Closed") -> 91 | M14: =COUNTIFS(Cleaned_Data!$D$2:$D$2601,I14,Cleaned_Data!$R$2:$R$2601,"Late") -> 5 | N14: =IF(L14=0,0,(L14-M14)/L14) -> 0.94505495
A15: 2025-08 | B15: =SUMIF(Cleaned_Data!$U$2:$U$2601,A15,Cleaned_Data!$K$2:$K$2601) -> 9123032.4 | C15: =COUNTIF(Cleaned_Data!$U$2:$U$2601,A15) -> 151 | I15: Vertex Digital Systems | J15: =SUMIF(Cleaned_Data!$D$2:$D$2601,I15,Cleaned_Data!$K$2:$K$2601) -> 9926619.4 | K15: =J15/$A$4 -> 0.062880803 | L15: =COUNTIFS(Cleaned_Data!$D$2:$D$2601,I15,Cleaned_Data!$Q$2:$Q$2601,"Closed") -> 85 | M15: =COUNTIFS(Cleaned_Data!$D$2:$D$2601,I15,Cleaned_Data!$R$2:$R$2601,"Late") -> 6 | N15: =IF(L15=0,0,(L15-M15)/L15) -> 0.92941176
A16: 2025-09 | B16: =SUMIF(Cleaned_Data!$U$2:$U$2601,A16,Cleaned_Data!$K$2:$K$2601) -> 8475355 | C16: =COUNTIF(Cleaned_Data!$U$2:$U$2601,A16) -> 152 | I16: StratEdge Partners | J16: =SUMIF(Cleaned_Data!$D$2:$D$2601,I16,Cleaned_Data!$K$2:$K$2601) -> 8985970.7 | K16: =J16/$A$4 -> 0.056922204 | L16: =COUNTIFS(Cleaned_Data!$D$2:$D$2601,I16,Cleaned_Data!$Q$2:$Q$2601,"Closed") -> 130 | M16: =COUNTIFS(Cleaned_Data!$D$2:$D$2601,I16,Cleaned_Data!$R$2:$R$2601,"Late") -> 10 | N16: =IF(L16=0,0,(L16-M16)/L16) -> 0.92307692
A17: 2025-10 | B17: =SUMIF(Cleaned_Data!$U$2:$U$2601,A17,Cleaned_Data!$K$2:$K$2601) -> 9567563.7 | C17: =COUNTIF(Cleaned_Data!$U$2:$U$2601,A17) -> 167 | I17: Urban Maintenance Co. | J17: =SUMIF(Cleaned_Data!$D$2:$D$2601,I17,Cleaned_Data!$K$2:$K$2601) -> 6287986.1 | K17: =J17/$A$4 -> 0.039831649 | L17: =COUNTIFS(Cleaned_Data!$D$2:$D$2601,I17,Cleaned_Data!$Q$2:$Q$2601,"Closed") -> 116 | M17: =COUNTIFS(Cleaned_Data!$D$2:$D$2601,I17,Cleaned_Data!$R$2:$R$2601,"Late") -> 19 | N17: =IF(L17=0,0,(L17-M17)/L17) -> 0.8362069
A18: 2025-11 | B18: =SUMIF(Cleaned_Data!$U$2:$U$2601,A18,Cleaned_Data!$K$2:$K$2601) -> 10569729 | C18: =COUNTIF(Cleaned_Data!$U$2:$U$2601,A18) -> 188 | I18: Metro Business Supplies | J18: =SUMIF(Cleaned_Data!$D$2:$D$2601,I18,Cleaned_Data!$K$2:$K$2601) -> 6022851 | K18: =J18/$A$4 -> 0.038152133 | L18: =COUNTIFS(Cleaned_Data!$D$2:$D$2601,I18,Cleaned_Data!$Q$2:$Q$2601,"Closed") -> 217 | M18: =COUNTIFS(Cleaned_Data!$D$2:$D$2601,I18,Cleaned_Data!$R$2:$R$2601,"Late") -> 48 | N18: =IF(L18=0,0,(L18-M18)/L18) -> 0.77880184
A19: 2025-12 | B19: =SUMIF(Cleaned_Data!$U$2:$U$2601,A19,Cleaned_Data!$K$2:$K$2601) -> 8023721.1 | C19: =COUNTIF(Cleaned_Data!$U$2:$U$2601,A19) -> 123 | I19: FacilityPro Services | J19: =SUMIF(Cleaned_Data!$D$2:$D$2601,I19,Cleaned_Data!$K$2:$K$2601) -> 5551035.8 | K19: =J19/$A$4 -> 0.03516339 | L19: =COUNTIFS(Cleaned_Data!$D$2:$D$2601,I19,Cleaned_Data!$Q$2:$Q$2601,"Closed") -> 106 | M19: =COUNTIFS(Cleaned_Data!$D$2:$D$2601,I19,Cleaned_Data!$R$2:$R$2601,"Late") -> 5 | N19: =IF(L19=0,0,(L19-M19)/L19) -> 0.95283019
... A23: 2026-04 | B23: =SUMIF(Cleaned_Data!$U$2:$U$2601,A23,Cleaned_Data!$K$2:$K$2601) -> 7781307.9 | C23: =COUNTIF(Cleaned_Data!$U$2:$U$2601,A23) -> 130 | I23: BrightReach Media | J23: =SUMIF(Cleaned_Data!$D$2:$D$2601,I23,Cleaned_Data!$K$2:$K$2601) -> 2616316.7 | K23: =J23/$A$4 -> 0.016573225 | L23: =COUNTIFS(Cleaned_Data!$D$2:$D$2601,I23,Cleaned_Data!$Q$2:$Q$2601,"Closed") -> 64 | M23: =COUNTIFS(Cleaned_Data!$D$2:$D$2601,I23,Cleaned_Data!$R$2:$R$2601,"Late") -> 3 | N23: =IF(L23=0,0,(L23-M23)/L23) -> 0.953125
A24: 2026-05 | B24: =SUMIF(Cleaned_Data!$U$2:$U$2601,A24,Cleaned_Data!$K$2:$K$2601) -> 8439161.4 | C24: =COUNTIF(Cleaned_Data!$U$2:$U$2601,A24) -> 134
A25: 2026-06 | B25: =SUMIF(Cleaned_Data!$U$2:$U$2601,A25,Cleaned_Data!$K$2:$K$2601) -> 8750483.3 | C25: =COUNTIF(Cleaned_Data!$U$2:$U$2601,A25) -> 135
I27: Department | J27: Spend_INR | K27: Spend_Share
I28: IT | J28: =SUMIF(Cleaned_Data!$E$2:$E$2601,I28,Cleaned_Data!$K$2:$K$2601) -> 44482040 | K28: =J28/$A$4 -> 0.28177432
A29: Category | B29: Spend_INR | C29: Spend_Share | I29: Operations | J29: =SUMIF(Cleaned_Data!$E$2:$E$2601,I29,Cleaned_Data!$K$2:$K$2601) -> 26975096 | K29: =J29/$A$4 -> 0.17087546
A30: Technology | B30: =SUMIF(Cleaned_Data!$F$2:$F$2601,A30,Cleaned_Data!$K$2:$K$2601) -> 58810102 | C30: =B30/$A$4 -> 0.37253634 | I30: Sales & Marketing | J30: =SUMIF(Cleaned_Data!$E$2:$E$2601,I30,Cleaned_Data!$K$2:$K$2601) -> 25504723 | K30: =J30/$A$4 -> 0.16156129
A31: Professional Services | B31: =SUMIF(Cleaned_Data!$F$2:$F$2601,A31,Cleaned_Data!$K$2:$K$2601) -> 41040093 | C31: =B31/$A$4 -> 0.25997109 | I31: Administration | J31: =SUMIF(Cleaned_Data!$E$2:$E$2601,I31,Cleaned_Data!$K$2:$K$2601) -> 21305236 | K31: =J31/$A$4 -> 0.13495938
A32: Office Supplies | B32: =SUMIF(Cleaned_Data!$F$2:$F$2601,A32,Cleaned_Data!$K$2:$K$2601) -> 24028236 | C32: =B32/$A$4 -> 0.15220839 | I32: Finance | J32: =SUMIF(Cleaned_Data!$E$2:$E$2601,I32,Cleaned_Data!$K$2:$K$2601) -> 21206343 | K32: =J32/$A$4 -> 0.13433293
A33: Facilities | B33: =SUMIF(Cleaned_Data!$F$2:$F$2601,A33,Cleaned_Data!$K$2:$K$2601) -> 18700032 | C33: =B33/$A$4 -> 0.11845655 | I33: Human Resources | J33: =SUMIF(Cleaned_Data!$E$2:$E$2601,I33,Cleaned_Data!$K$2:$K$2601) -> 18390631 | K33: =J33/$A$4 -> 0.11649662
A34: Safety | B34: =SUMIF(Cleaned_Data!$F$2:$F$2601,A34,Cleaned_Data!$K$2:$K$2601) -> 9877382.2 | C34: =B34/$A$4 -> 0.062568907
A35: Marketing | B35: =SUMIF(Cleaned_Data!$F$2:$F$2601,A35,Cleaned_Data!$K$2:$K$2601) -> 5408222.2 | C35: =B35/$A$4 -> 0.034258728
A39: Item_ID | B39: Item_Description | C39: Lowest_Price_Vendor | D39: Avg_Low_Price | E39: Highest_Price_Vendor | F39: Avg_High_Price | G39: Price_Gap_%
A40: ITM008 | B40: Network Switch - 24 Port | C40: CoreTech Solutions | D40: 15401.436 | E40: Vertex Digital Systems | F40: 18474.241 | G40: 0.19951421
A41: ITM007 | B41: USB-C Docking Station | C41: CoreTech Solutions | D41: 8141.0154 | E41: Vertex Digital Systems | F41: 9727.9928 | G41: 0.19493604
A42: ITM006 | B42: Business Laptop - Standard | C42: CoreTech Solutions | D42: 53554.882 | E42: Vertex Digital Systems | F42: 63476.974 | G42: 0.18526962
A43: ITM009 | B43: Annual Software License | C43: CoreTech Solutions | D43: 20691.944 | E43: Vertex Digital Systems | F43: 24464.364 | G43: 0.18231351
A44: ITM004 | B44: Wireless Keyboard & Mouse | C44: CoreTech Solutions | D44: 1696.7586 | E44: Vertex Digital Systems | F44: 1993.3271 | G44: 0.17478532
A45: ITM005 | B45: 24-inch Business Monitor | C45: CoreTech Solutions | D45: 10235.147 | E45: Vertex Digital Systems | F45: 12018.929 | G45: 0.17428012
A46: ITM001 | B46: A4 Copier Paper - 500 Sheets | C46: Metro Business Supplies | D46: 230.2027 | E46: Prime Workplace India | F46: 267.39769 | G46: 0.16157495
A47: ITM002 | B47: Black Toner Cartridge | C47: Metro Business Supplies | D47: 2979.9648 | E47: Prime Workplace India | F47: 3445.6963 | G47: 0.1562876
A48: ITM003 | B48: Ergonomic Office Chair | C48: Metro Business Supplies | D48: 7369.4118 | E48: Prime Workplace India | F48: 8482.2012 | G48: 0.15100111
A49: ITM012 | B49: LED Panel Light | C49: Urban Maintenance Co. | D49: 1587.913 | E49: Prime Workplace India | F49: 1780.162 | G49: 0.1210702

Sheet Dashboard
A1: Vendor Spend & Procurement Analytics | N1: Vendor | O1: On_Time_Pct
N2: CoreTech Solutions | O2: 77.6
N3: Insight Advisory Services | O3: 93.9
A4: Total Spend | D4: Total POs | G4: On-Time Delivery | J4: Top 3 Vendor Share | N4: Prime Workplace India | O4: 96.1
A5: ="₹"&TEXT(Excel_Analysis!A4,"#,##0") -> ₹157,864,068 | D5: =TEXT(Excel_Analysis!B4,"#,##0") -> 2,600 | G5: =TEXT(Excel_Analysis!D4,"0.0%") -> 90.2% | J5: =TEXT(Excel_Analysis!F4,"0.0%") -> 37.1% | N5: Nexa Technologies | O5: 88.6
N6: Apex Office Solutions | O6: 92.9
N7: TalentBridge Consulting | O7: 95.3
N8: SecureNet Systems | O8: 94.5
N9: Vertex Digital Systems | O9: 92.9
A41: Validated Findings & Recommendations
A42: 1. Technology is the largest spend category at ₹58,810,102, representing 37.3% of total procurement spend.
A43: 2. CoreTech Solutions is the largest vendor at ₹25,491,861 (16.1% of spend), but its on-time delivery rate is only 77.6%.
A44: 3. The top three vendors account for 37.1% of total spend, showing a meaningful but not extreme concentration risk.
A45: 4. The largest same-item price gap is for Network Switch - 24 Port: average prices differ by 20.0% between CoreTech Solutions and Vertex Digital Systems.
A46: 5. Metro Business Supplies offers relatively lower office-supply pricing but has an on-time rate of 77.9%; vendor selection should balance cost and delivery reliability.
A47: 6. Vertex Digital Systems has an on-time rate of 92.9%, materially stronger than CoreTech, but generally at higher technology-item prices.
A50: Recommendation: use item-level price benchmarks during vendor negotiations, review high-spend vendors with weaker delivery performance, and consider split-award sourcing where lower price and higher reliability come from different vendors.

Sheet Project_Guide
A1: VENDOR SPEND & PROCUREMENT ANALYTICS
A2: Business Scenario | B2: A multi-location company wants to understand procurement spend, vendor concentration, price inconsistencies, and delivery performance to identify cost-saving and vendor-management opportunities.
A3: Target Role | B3: Entry-level Business Analyst / Data Analyst
A4: Tools Used | B4: Excel, SQL, Power BI
A5: Data Period | B5: January 2025 to June 2026
A6: Dataset Size | B6: 2,600 purchase-order line records
A7: Currency | B7: Indian Rupees (INR)
A9: Workflow | B9: Raw data → Data cleaning → Excel analysis → SQL analysis → Power BI-ready model → Business insights
A11: Business Questions
A12: 1 | B12: How much is the company spending, and how is spend changing over time?
A13: 2 | B13: Which vendors, categories, departments, and regions account for the most spend?
A14: 3 | B14: Is procurement overly dependent on a small number of vendors?
A15: 4 | B15: Are different vendors charging materially different prices for the same items?
A16: 5 | B16: Which vendors provide the best balance of cost and delivery reliability?
A17: 6 | B17: Where are late deliveries concentrated?
A18: 7 | B18: What practical actions could management take based on the findings?
A20: Cleaning Performed | B20: Trimmed vendor names; standardized category capitalization; standardized payment terms; standardized buyer names; retained legitimate blank actual-delivery dates for open POs.
A22: Portfolio Note | B22: This is a synthetic portfolio dataset created to demonstrate a realistic procurement analytics workflow. Findings shown in the workbook are calculated from the generated data.

Sheet Data_Dictionary
A1: Field | B1: Description
A2: PO_Number | B2: Unique purchase-order line identifier in this project.
A3: PO_Date | B3: Date the purchase order was created.
A4: Vendor_ID | B4: Unique vendor identifier.
A5: Vendor_Name | B5: Vendor supplying the product or service.
A6: Department | B6: Internal department responsible for the purchase.
A7: Category | B7: High-level procurement category.
A8: Item_ID | B8: Unique item/service identifier.
A9: Item_Description | B9: Description of the purchased item or service.
A10: Quantity | B10: Number of units purchased.
A11: Unit_Price_INR | B11: Price paid per unit in INR.
A12: PO_Amount_INR | B12: Quantity multiplied by unit price.
... A24: On_Time_Flag | B24: 1 for on-time closed PO, 0 for late closed PO, blank for open PO.
